<annotation>
  <filename>1647.jpg</filename>
  <size>
    <width>960</width>
    <height>540</height>
    <depth>3</depth>
  </size>
  <object>
    <name>pedestrian</name>
    <bndbox>
      <xmin>714</xmin>
      <ymin>21</ymin>
      <xmax>740</xmax>
      <ymax>91</ymax>
    </bndbox>
  </object>
  <object>
    <name>pedestrian</name>
    <bndbox>
      <xmin>747</xmin>
      <ymin>39</ymin>
      <xmax>776</xmax>
      <ymax>115</ymax>
    </bndbox>
  </object>
  <object>
    <name>pedestrian</name>
    <bndbox>
      <xmin>501</xmin>
      <ymin>22</ymin>
      <xmax>526</xmax>
      <ymax>91</ymax>
    </bndbox>
  </object>
  <object>
    <name>pedestrian</name>
    <bndbox>
      <xmin>431</xmin>
      <ymin>17</ymin>
      <xmax>456</xmax>
      <ymax>84</ymax>
    </bndbox>
  </object>
  <object>
    <name>pedestrian</name>
    <bndbox>
      <xmin>381</xmin>
      <ymin>131</ymin>
      <xmax>417</xmax>
      <ymax>231</ymax>
    </bndbox>
  </object>
  <object>
    <name>pedestrian</name>
    <bndbox>
      <xmin>84</xmin>
      <ymin>144</ymin>
      <xmax>130</xmax>
      <ymax>245</ymax>
    </bndbox>
  </object>
  <object>
    <name>pedestrian</name>
    <bndbox>
      <xmin>752</xmin>
      <ymin>19</ymin>
      <xmax>780</xmax>
      <ymax>90</ymax>
    </bndbox>
  </object>
  <object>
    <name>pedestrian</name>
    <bndbox>
      <xmin>438</xmin>
      <ymin>132</ymin>
      <xmax>472</xmax>
      <ymax>233</ymax>
    </bndbox>
  </object>
  <object>
    <name>pedestrian</name>
    <bndbox>
      <xmin>641</xmin>
      <ymin>104</ymin>
      <xmax>672</xmax>
      <ymax>196</ymax>
    </bndbox>
  </object>
  <object>
    <name>pedestrian</name>
    <bndbox>
      <xmin>262</xmin>
      <ymin>89</ymin>
      <xmax>295</xmax>
      <ymax>176</ymax>
    </bndbox>
  </object>
  <object>
    <name>pedestrian</name>
    <bndbox>
      <xmin>768</xmin>
      <ymin>36</ymin>
      <xmax>798</xmax>
      <ymax>112</ymax>
    </bndbox>
  </object>
  <object>
    <name>pedestrian</name>
    <bndbox>
      <xmin>377</xmin>
      <ymin>50</ymin>
      <xmax>405</xmax>
      <ymax>126</ymax>
    </bndbox>
  </object>
  <object>
    <name>pedestrian</name>
    <bndbox>
      <xmin>316</xmin>
      <ymin>127</ymin>
      <xmax>352</xmax>
      <ymax>225</ymax>
    </bndbox>
  </object>
  <object>
    <name>pedestrian</name>
    <bndbox>
      <xmin>347</xmin>
      <ymin>163</ymin>
      <xmax>385</xmax>
      <ymax>272</ymax>
    </bndbox>
  </object>
  <object>
    <name>pedestrian</name>
    <bndbox>
      <xmin>820</xmin>
      <ymin>164</ymin>
      <xmax>863</xmax>
      <ymax>274</ymax>
    </bndbox>
  </object>
  <object>
    <name>pedestrian</name>
    <bndbox>
      <xmin>245</xmin>
      <ymin>98</ymin>
      <xmax>279</xmax>
      <ymax>187</ymax>
    </bndbox>
  </object>
  <object>
    <name>pedestrian</name>
    <bndbox>
      <xmin>484</xmin>
      <ymin>15</ymin>
      <xmax>508</xmax>
      <ymax>82</ymax>
    </bndbox>
  </object>
  <object>
    <name>pedestrian</name>
    <bndbox>
      <xmin>910</xmin>
      <ymin>71</ymin>
      <xmax>954</xmax>
      <ymax>161</ymax>
    </bndbox>
  </object>
  <object>
    <name>pedestrian</name>
    <bndbox>
      <xmin>506</xmin>
      <ymin>-4</ymin>
      <xmax>528</xmax>
      <ymax>58</ymax>
    </bndbox>
  </object>
</annotation>
