<annotation>
  <filename>19.jpg</filename>
  <size>
    <width>960</width>
    <height>540</height>
    <depth>3</depth>
  </size>
  <object>
    <name>pedestrian</name>
    <bndbox>
      <xmin>40</xmin>
      <ymin>439</ymin>
      <xmax>117</xmax>
      <ymax>629</ymax>
    </bndbox>
  </object>
  <object>
    <name>pedestrian</name>
    <bndbox>
      <xmin>89</xmin>
      <ymin>166</ymin>
      <xmax>137</xmax>
      <ymax>272</ymax>
    </bndbox>
  </object>
  <object>
    <name>pedestrian</name>
    <bndbox>
      <xmin>180</xmin>
      <ymin>101</ymin>
      <xmax>216</xmax>
      <ymax>190</ymax>
    </bndbox>
  </object>
  <object>
    <name>pedestrian</name>
    <bndbox>
      <xmin>389</xmin>
      <ymin>98</ymin>
      <xmax>421</xmax>
      <ymax>188</ymax>
    </bndbox>
  </object>
  <object>
    <name>pedestrian</name>
    <bndbox>
      <xmin>426</xmin>
      <ymin>105</ymin>
      <xmax>458</xmax>
      <ymax>198</ymax>
    </bndbox>
  </object>
  <object>
    <name>pedestrian</name>
    <bndbox>
      <xmin>400</xmin>
      <ymin>222</ymin>
      <xmax>443</xmax>
      <ymax>347</ymax>
    </bndbox>
  </object>
  <object>
    <name>pedestrian</name>
    <bndbox>
      <xmin>370</xmin>
      <ymin>447</ymin>
      <xmax>433</xmax>
      <ymax>626</ymax>
    </bndbox>
  </object>
  <object>
    <name>pedestrian</name>
    <bndbox>
      <xmin>810</xmin>
      <ymin>334</ymin>
      <xmax>868</xmax>
      <ymax>490</ymax>
    </bndbox>
  </object>
  <object>
    <name>pedestrian</name>
    <bndbox>
      <xmin>913</xmin>
      <ymin>81</ymin>
      <xmax>959</xmax>
      <ymax>174</ymax>
    </bndbox>
  </object>
  <object>
    <name>pedestrian</name>
    <bndbox>
      <xmin>820</xmin>
      <ymin>48</ymin>
      <xmax>853</xmax>
      <ymax>128</ymax>
    </bndbox>
  </object>
  <object>
    <name>pedestrian</name>
    <bndbox>
      <xmin>739</xmin>
      <ymin>7</ymin>
      <xmax>765</xmax>
      <ymax>75</ymax>
    </bndbox>
  </object>
  <object>
    <name>pedestrian</name>
    <bndbox>
      <xmin>466</xmin>
      <ymin>30</ymin>
      <xmax>492</xmax>
      <ymax>102</ymax>
    </bndbox>
  </object>
  <object>
    <name>pedestrian</name>
    <bndbox>
      <xmin>904</xmin>
      <ymin>150</ymin>
      <xmax>954</xmax>
      <ymax>258</ymax>
    </bndbox>
  </object>
  <object>
    <name>pedestrian</name>
    <bndbox>
      <xmin>875</xmin>
      <ymin>304</ymin>
      <xmax>936</xmax>
      <ymax>453</ymax>
    </bndbox>
  </object>
</annotation>
