<annotation>
  <filename>3519.jpg</filename>
  <size>
    <width>960</width>
    <height>540</height>
    <depth>3</depth>
  </size>
  <object>
    <name>pedestrian</name>
    <bndbox>
      <xmin>729</xmin>
      <ymin>18</ymin>
      <xmax>755</xmax>
      <ymax>88</ymax>
    </bndbox>
  </object>
  <object>
    <name>pedestrian</name>
    <bndbox>
      <xmin>155</xmin>
      <ymin>138</ymin>
      <xmax>196</xmax>
      <ymax>237</ymax>
    </bndbox>
  </object>
  <object>
    <name>pedestrian</name>
    <bndbox>
      <xmin>171</xmin>
      <ymin>148</ymin>
      <xmax>212</xmax>
      <ymax>250</ymax>
    </bndbox>
  </object>
  <object>
    <name>pedestrian</name>
    <bndbox>
      <xmin>738</xmin>
      <ymin>88</ymin>
      <xmax>770</xmax>
      <ymax>177</ymax>
    </bndbox>
  </object>
  <object>
    <name>pedestrian</name>
    <bndbox>
      <xmin>-16</xmin>
      <ymin>196</ymin>
      <xmax>44</xmax>
      <ymax>312</ymax>
    </bndbox>
  </object>
  <object>
    <name>pedestrian</name>
    <bndbox>
      <xmin>624</xmin>
      <ymin>131</ymin>
      <xmax>656</xmax>
      <ymax>231</ymax>
    </bndbox>
  </object>
  <object>
    <name>pedestrian</name>
    <bndbox>
      <xmin>418</xmin>
      <ymin>102</ymin>
      <xmax>451</xmax>
      <ymax>194</ymax>
    </bndbox>
  </object>
  <object>
    <name>pedestrian</name>
    <bndbox>
      <xmin>452</xmin>
      <ymin>105</ymin>
      <xmax>484</xmax>
      <ymax>197</ymax>
    </bndbox>
  </object>
  <object>
    <name>pedestrian</name>
    <bndbox>
      <xmin>644</xmin>
      <ymin>164</ymin>
      <xmax>680</xmax>
      <ymax>273</ymax>
    </bndbox>
  </object>
  <object>
    <name>pedestrian</name>
    <bndbox>
      <xmin>210</xmin>
      <ymin>103</ymin>
      <xmax>246</xmax>
      <ymax>193</ymax>
    </bndbox>
  </object>
  <object>
    <name>pedestrian</name>
    <bndbox>
      <xmin>196</xmin>
      <ymin>90</ymin>
      <xmax>231</xmax>
      <ymax>177</ymax>
    </bndbox>
  </object>
  <object>
    <name>pedestrian</name>
    <bndbox>
      <xmin>356</xmin>
      <ymin>65</ymin>
      <xmax>386</xmax>
      <ymax>146</ymax>
    </bndbox>
  </object>
  <object>
    <name>pedestrian</name>
    <bndbox>
      <xmin>468</xmin>
      <ymin>8</ymin>
      <xmax>491</xmax>
      <ymax>74</ymax>
    </bndbox>
  </object>
  <object>
    <name>pedestrian</name>
    <bndbox>
      <xmin>206</xmin>
      <ymin>130</ymin>
      <xmax>245</xmax>
      <ymax>228</ymax>
    </bndbox>
  </object>
  <object>
    <name>pedestrian</name>
    <bndbox>
      <xmin>177</xmin>
      <ymin>124</ymin>
      <xmax>216</xmax>
      <ymax>219</ymax>
    </bndbox>
  </object>
  <object>
    <name>pedestrian</name>
    <bndbox>
      <xmin>629</xmin>
      <ymin>419</ymin>
      <xmax>687</xmax>
      <ymax>593</ymax>
    </bndbox>
  </object>
  <object>
    <name>pedestrian</name>
    <bndbox>
      <xmin>47</xmin>
      <ymin>142</ymin>
      <xmax>95</xmax>
      <ymax>243</ymax>
    </bndbox>
  </object>
  <object>
    <name>pedestrian</name>
    <bndbox>
      <xmin>897</xmin>
      <ymin>68</ymin>
      <xmax>939</xmax>
      <ymax>157</ymax>
    </bndbox>
  </object>
  <object>
    <name>pedestrian</name>
    <bndbox>
      <xmin>918</xmin>
      <ymin>52</ymin>
      <xmax>961</xmax>
      <ymax>138</ymax>
    </bndbox>
  </object>
</annotation>
