<annotation>
  <filename>2029.jpg</filename>
  <size>
    <width>960</width>
    <height>540</height>
    <depth>3</depth>
  </size>
  <object>
    <name>pedestrian</name>
    <bndbox>
      <xmin>526</xmin>
      <ymin>30</ymin>
      <xmax>551</xmax>
      <ymax>102</ymax>
    </bndbox>
  </object>
  <object>
    <name>pedestrian</name>
    <bndbox>
      <xmin>650</xmin>
      <ymin>157</ymin>
      <xmax>686</xmax>
      <ymax>264</ymax>
    </bndbox>
  </object>
  <object>
    <name>pedestrian</name>
    <bndbox>
      <xmin>435</xmin>
      <ymin>32</ymin>
      <xmax>461</xmax>
      <ymax>104</ymax>
    </bndbox>
  </object>
  <object>
    <name>pedestrian</name>
    <bndbox>
      <xmin>544</xmin>
      <ymin>23</ymin>
      <xmax>568</xmax>
      <ymax>93</ymax>
    </bndbox>
  </object>
  <object>
    <name>pedestrian</name>
    <bndbox>
      <xmin>581</xmin>
      <ymin>101</ymin>
      <xmax>610</xmax>
      <ymax>193</ymax>
    </bndbox>
  </object>
  <object>
    <name>pedestrian</name>
    <bndbox>
      <xmin>618</xmin>
      <ymin>109</ymin>
      <xmax>649</xmax>
      <ymax>203</ymax>
    </bndbox>
  </object>
  <object>
    <name>pedestrian</name>
    <bndbox>
      <xmin>471</xmin>
      <ymin>65</ymin>
      <xmax>499</xmax>
      <ymax>147</ymax>
    </bndbox>
  </object>
  <object>
    <name>pedestrian</name>
    <bndbox>
      <xmin>699</xmin>
      <ymin>77</ymin>
      <xmax>729</xmax>
      <ymax>163</ymax>
    </bndbox>
  </object>
  <object>
    <name>pedestrian</name>
    <bndbox>
      <xmin>847</xmin>
      <ymin>92</ymin>
      <xmax>886</xmax>
      <ymax>183</ymax>
    </bndbox>
  </object>
  <object>
    <name>pedestrian</name>
    <bndbox>
      <xmin>375</xmin>
      <ymin>47</ymin>
      <xmax>403</xmax>
      <ymax>123</ymax>
    </bndbox>
  </object>
  <object>
    <name>pedestrian</name>
    <bndbox>
      <xmin>-12</xmin>
      <ymin>189</ymin>
      <xmax>46</xmax>
      <ymax>302</ymax>
    </bndbox>
  </object>
  <object>
    <name>pedestrian</name>
    <bndbox>
      <xmin>193</xmin>
      <ymin>172</ymin>
      <xmax>236</xmax>
      <ymax>280</ymax>
    </bndbox>
  </object>
  <object>
    <name>pedestrian</name>
    <bndbox>
      <xmin>205</xmin>
      <ymin>261</ymin>
      <xmax>257</xmax>
      <ymax>393</ymax>
    </bndbox>
  </object>
</annotation>
