<annotation>
  <filename>2477.jpg</filename>
  <size>
    <width>960</width>
    <height>540</height>
    <depth>3</depth>
  </size>
  <object>
    <name>pedestrian</name>
    <bndbox>
      <xmin>687</xmin>
      <ymin>295</ymin>
      <xmax>736</xmax>
      <ymax>438</ymax>
    </bndbox>
  </object>
  <object>
    <name>pedestrian</name>
    <bndbox>
      <xmin>634</xmin>
      <ymin>506</ymin>
      <xmax>699</xmax>
      <ymax>712</ymax>
    </bndbox>
  </object>
  <object>
    <name>pedestrian</name>
    <bndbox>
      <xmin>641</xmin>
      <ymin>7</ymin>
      <xmax>664</xmax>
      <ymax>73</ymax>
    </bndbox>
  </object>
  <object>
    <name>pedestrian</name>
    <bndbox>
      <xmin>417</xmin>
      <ymin>46</ymin>
      <xmax>445</xmax>
      <ymax>122</ymax>
    </bndbox>
  </object>
  <object>
    <name>pedestrian</name>
    <bndbox>
      <xmin>741</xmin>
      <ymin>485</ymin>
      <xmax>807</xmax>
      <ymax>690</ymax>
    </bndbox>
  </object>
  <object>
    <name>pedestrian</name>
    <bndbox>
      <xmin>386</xmin>
      <ymin>137</ymin>
      <xmax>422</xmax>
      <ymax>238</ymax>
    </bndbox>
  </object>
  <object>
    <name>pedestrian</name>
    <bndbox>
      <xmin>477</xmin>
      <ymin>66</ymin>
      <xmax>505</xmax>
      <ymax>148</ymax>
    </bndbox>
  </object>
  <object>
    <name>pedestrian</name>
    <bndbox>
      <xmin>508</xmin>
      <ymin>64</ymin>
      <xmax>536</xmax>
      <ymax>146</ymax>
    </bndbox>
  </object>
  <object>
    <name>pedestrian</name>
    <bndbox>
      <xmin>728</xmin>
      <ymin>54</ymin>
      <xmax>757</xmax>
      <ymax>134</ymax>
    </bndbox>
  </object>
  <object>
    <name>pedestrian</name>
    <bndbox>
      <xmin>758</xmin>
      <ymin>56</ymin>
      <xmax>788</xmax>
      <ymax>136</ymax>
    </bndbox>
  </object>
  <object>
    <name>pedestrian</name>
    <bndbox>
      <xmin>858</xmin>
      <ymin>228</ymin>
      <xmax>910</xmax>
      <ymax>355</ymax>
    </bndbox>
  </object>
  <object>
    <name>pedestrian</name>
    <bndbox>
      <xmin>523</xmin>
      <ymin>384</ymin>
      <xmax>575</xmax>
      <ymax>547</ymax>
    </bndbox>
  </object>
  <object>
    <name>pedestrian</name>
    <bndbox>
      <xmin>373</xmin>
      <ymin>40</ymin>
      <xmax>400</xmax>
      <ymax>114</ymax>
    </bndbox>
  </object>
  <object>
    <name>pedestrian</name>
    <bndbox>
      <xmin>774</xmin>
      <ymin>26</ymin>
      <xmax>803</xmax>
      <ymax>100</ymax>
    </bndbox>
  </object>
</annotation>
