<annotation>
  <filename>2822.jpg</filename>
  <size>
    <width>960</width>
    <height>540</height>
    <depth>3</depth>
  </size>
  <object>
    <name>pedestrian</name>
    <bndbox>
      <xmin>700</xmin>
      <ymin>174</ymin>
      <xmax>739</xmax>
      <ymax>285</ymax>
    </bndbox>
  </object>
  <object>
    <name>pedestrian</name>
    <bndbox>
      <xmin>294</xmin>
      <ymin>348</ymin>
      <xmax>352</xmax>
      <ymax>502</ymax>
    </bndbox>
  </object>
  <object>
    <name>pedestrian</name>
    <bndbox>
      <xmin>739</xmin>
      <ymin>419</ymin>
      <xmax>802</xmax>
      <ymax>598</ymax>
    </bndbox>
  </object>
  <object>
    <name>pedestrian</name>
    <bndbox>
      <xmin>165</xmin>
      <ymin>205</ymin>
      <xmax>212</xmax>
      <ymax>322</ymax>
    </bndbox>
  </object>
  <object>
    <name>pedestrian</name>
    <bndbox>
      <xmin>862</xmin>
      <ymin>84</ymin>
      <xmax>902</xmax>
      <ymax>175</ymax>
    </bndbox>
  </object>
  <object>
    <name>pedestrian</name>
    <bndbox>
      <xmin>651</xmin>
      <ymin>230</ymin>
      <xmax>693</xmax>
      <ymax>357</ymax>
    </bndbox>
  </object>
  <object>
    <name>pedestrian</name>
    <bndbox>
      <xmin>649</xmin>
      <ymin>393</ymin>
      <xmax>706</xmax>
      <ymax>560</ymax>
    </bndbox>
  </object>
  <object>
    <name>pedestrian</name>
    <bndbox>
      <xmin>340</xmin>
      <ymin>70</ymin>
      <xmax>370</xmax>
      <ymax>152</ymax>
    </bndbox>
  </object>
  <object>
    <name>pedestrian</name>
    <bndbox>
      <xmin>809</xmin>
      <ymin>424</ymin>
      <xmax>874</xmax>
      <ymax>609</ymax>
    </bndbox>
  </object>
</annotation>
