<annotation>
  <filename>3678.jpg</filename>
  <size>
    <width>960</width>
    <height>540</height>
    <depth>3</depth>
  </size>
  <object>
    <name>pedestrian</name>
    <bndbox>
      <xmin>501</xmin>
      <ymin>79</ymin>
      <xmax>530</xmax>
      <ymax>164</ymax>
    </bndbox>
  </object>
  <object>
    <name>pedestrian</name>
    <bndbox>
      <xmin>828</xmin>
      <ymin>13</ymin>
      <xmax>859</xmax>
      <ymax>85</ymax>
    </bndbox>
  </object>
  <object>
    <name>pedestrian</name>
    <bndbox>
      <xmin>413</xmin>
      <ymin>326</ymin>
      <xmax>465</xmax>
      <ymax>475</ymax>
    </bndbox>
  </object>
  <object>
    <name>pedestrian</name>
    <bndbox>
      <xmin>531</xmin>
      <ymin>17</ymin>
      <xmax>555</xmax>
      <ymax>85</ymax>
    </bndbox>
  </object>
  <object>
    <name>pedestrian</name>
    <bndbox>
      <xmin>555</xmin>
      <ymin>23</ymin>
      <xmax>579</xmax>
      <ymax>93</ymax>
    </bndbox>
  </object>
  <object>
    <name>pedestrian</name>
    <bndbox>
      <xmin>793</xmin>
      <ymin>47</ymin>
      <xmax>825</xmax>
      <ymax>126</ymax>
    </bndbox>
  </object>
  <object>
    <name>pedestrian</name>
    <bndbox>
      <xmin>398</xmin>
      <ymin>44</ymin>
      <xmax>426</xmax>
      <ymax>119</ymax>
    </bndbox>
  </object>
  <object>
    <name>pedestrian</name>
    <bndbox>
      <xmin>378</xmin>
      <ymin>33</ymin>
      <xmax>404</xmax>
      <ymax>104</ymax>
    </bndbox>
  </object>
  <object>
    <name>pedestrian</name>
    <bndbox>
      <xmin>62</xmin>
      <ymin>177</ymin>
      <xmax>112</xmax>
      <ymax>286</ymax>
    </bndbox>
  </object>
  <object>
    <name>pedestrian</name>
    <bndbox>
      <xmin>766</xmin>
      <ymin>184</ymin>
      <xmax>808</xmax>
      <ymax>298</ymax>
    </bndbox>
  </object>
  <object>
    <name>pedestrian</name>
    <bndbox>
      <xmin>378</xmin>
      <ymin>50</ymin>
      <xmax>406</xmax>
      <ymax>127</ymax>
    </bndbox>
  </object>
  <object>
    <name>pedestrian</name>
    <bndbox>
      <xmin>807</xmin>
      <ymin>179</ymin>
      <xmax>850</xmax>
      <ymax>292</ymax>
    </bndbox>
  </object>
  <object>
    <name>pedestrian</name>
    <bndbox>
      <xmin>278</xmin>
      <ymin>85</ymin>
      <xmax>310</xmax>
      <ymax>171</ymax>
    </bndbox>
  </object>
  <object>
    <name>pedestrian</name>
    <bndbox>
      <xmin>862</xmin>
      <ymin>181</ymin>
      <xmax>910</xmax>
      <ymax>296</ymax>
    </bndbox>
  </object>
  <object>
    <name>pedestrian</name>
    <bndbox>
      <xmin>408</xmin>
      <ymin>10</ymin>
      <xmax>432</xmax>
      <ymax>76</ymax>
    </bndbox>
  </object>
  <object>
    <name>pedestrian</name>
    <bndbox>
      <xmin>701</xmin>
      <ymin>436</ymin>
      <xmax>763</xmax>
      <ymax>618</ymax>
    </bndbox>
  </object>
  <object>
    <name>pedestrian</name>
    <bndbox>
      <xmin>770</xmin>
      <ymin>445</ymin>
      <xmax>835</xmax>
      <ymax>635</ymax>
    </bndbox>
  </object>
</annotation>
