<annotation>
  <filename>3699.jpg</filename>
  <size>
    <width>960</width>
    <height>540</height>
    <depth>3</depth>
  </size>
  <object>
    <name>pedestrian</name>
    <bndbox>
      <xmin>463</xmin>
      <ymin>92</ymin>
      <xmax>494</xmax>
      <ymax>182</ymax>
    </bndbox>
  </object>
  <object>
    <name>pedestrian</name>
    <bndbox>
      <xmin>833</xmin>
      <ymin>4</ymin>
      <xmax>864</xmax>
      <ymax>74</ymax>
    </bndbox>
  </object>
  <object>
    <name>pedestrian</name>
    <bndbox>
      <xmin>372</xmin>
      <ymin>374</ymin>
      <xmax>428</xmax>
      <ymax>534</ymax>
    </bndbox>
  </object>
  <object>
    <name>pedestrian</name>
    <bndbox>
      <xmin>550</xmin>
      <ymin>10</ymin>
      <xmax>573</xmax>
      <ymax>76</ymax>
    </bndbox>
  </object>
  <object>
    <name>pedestrian</name>
    <bndbox>
      <xmin>565</xmin>
      <ymin>12</ymin>
      <xmax>588</xmax>
      <ymax>79</ymax>
    </bndbox>
  </object>
  <object>
    <name>pedestrian</name>
    <bndbox>
      <xmin>804</xmin>
      <ymin>36</ymin>
      <xmax>835</xmax>
      <ymax>113</ymax>
    </bndbox>
  </object>
  <object>
    <name>pedestrian</name>
    <bndbox>
      <xmin>422</xmin>
      <ymin>35</ymin>
      <xmax>448</xmax>
      <ymax>108</ymax>
    </bndbox>
  </object>
  <object>
    <name>pedestrian</name>
    <bndbox>
      <xmin>400</xmin>
      <ymin>28</ymin>
      <xmax>426</xmax>
      <ymax>99</ymax>
    </bndbox>
  </object>
  <object>
    <name>pedestrian</name>
    <bndbox>
      <xmin>7</xmin>
      <ymin>198</ymin>
      <xmax>65</xmax>
      <ymax>314</ymax>
    </bndbox>
  </object>
  <object>
    <name>pedestrian</name>
    <bndbox>
      <xmin>778</xmin>
      <ymin>163</ymin>
      <xmax>818</xmax>
      <ymax>273</ymax>
    </bndbox>
  </object>
  <object>
    <name>pedestrian</name>
    <bndbox>
      <xmin>414</xmin>
      <ymin>41</ymin>
      <xmax>441</xmax>
      <ymax>115</ymax>
    </bndbox>
  </object>
  <object>
    <name>pedestrian</name>
    <bndbox>
      <xmin>786</xmin>
      <ymin>195</ymin>
      <xmax>830</xmax>
      <ymax>312</ymax>
    </bndbox>
  </object>
  <object>
    <name>pedestrian</name>
    <bndbox>
      <xmin>326</xmin>
      <ymin>77</ymin>
      <xmax>357</xmax>
      <ymax>162</ymax>
    </bndbox>
  </object>
  <object>
    <name>pedestrian</name>
    <bndbox>
      <xmin>841</xmin>
      <ymin>199</ymin>
      <xmax>889</xmax>
      <ymax>318</ymax>
    </bndbox>
  </object>
  <object>
    <name>pedestrian</name>
    <bndbox>
      <xmin>406</xmin>
      <ymin>9</ymin>
      <xmax>430</xmax>
      <ymax>74</ymax>
    </bndbox>
  </object>
  <object>
    <name>pedestrian</name>
    <bndbox>
      <xmin>724</xmin>
      <ymin>409</ymin>
      <xmax>785</xmax>
      <ymax>583</ymax>
    </bndbox>
  </object>
  <object>
    <name>pedestrian</name>
    <bndbox>
      <xmin>794</xmin>
      <ymin>417</ymin>
      <xmax>858</xmax>
      <ymax>598</ymax>
    </bndbox>
  </object>
  <object>
    <name>pedestrian</name>
    <bndbox>
      <xmin>533</xmin>
      <ymin>-4</ymin>
      <xmax>555</xmax>
      <ymax>58</ymax>
    </bndbox>
  </object>
</annotation>
