<annotation>
  <filename>3750.jpg</filename>
  <size>
    <width>960</width>
    <height>540</height>
    <depth>3</depth>
  </size>
  <object>
    <name>pedestrian</name>
    <bndbox>
      <xmin>373</xmin>
      <ymin>120</ymin>
      <xmax>407</xmax>
      <ymax>216</ymax>
    </bndbox>
  </object>
  <object>
    <name>pedestrian</name>
    <bndbox>
      <xmin>244</xmin>
      <ymin>496</ymin>
      <xmax>315</xmax>
      <ymax>695</ymax>
    </bndbox>
  </object>
  <object>
    <name>pedestrian</name>
    <bndbox>
      <xmin>600</xmin>
      <ymin>-5</ymin>
      <xmax>621</xmax>
      <ymax>57</ymax>
    </bndbox>
  </object>
  <object>
    <name>pedestrian</name>
    <bndbox>
      <xmin>824</xmin>
      <ymin>12</ymin>
      <xmax>855</xmax>
      <ymax>84</ymax>
    </bndbox>
  </object>
  <object>
    <name>pedestrian</name>
    <bndbox>
      <xmin>458</xmin>
      <ymin>22</ymin>
      <xmax>483</xmax>
      <ymax>91</ymax>
    </bndbox>
  </object>
  <object>
    <name>pedestrian</name>
    <bndbox>
      <xmin>439</xmin>
      <ymin>13</ymin>
      <xmax>463</xmax>
      <ymax>80</ymax>
    </bndbox>
  </object>
  <object>
    <name>pedestrian</name>
    <bndbox>
      <xmin>818</xmin>
      <ymin>124</ymin>
      <xmax>857</xmax>
      <ymax>223</ymax>
    </bndbox>
  </object>
  <object>
    <name>pedestrian</name>
    <bndbox>
      <xmin>493</xmin>
      <ymin>23</ymin>
      <xmax>518</xmax>
      <ymax>93</ymax>
    </bndbox>
  </object>
  <object>
    <name>pedestrian</name>
    <bndbox>
      <xmin>745</xmin>
      <ymin>245</ymin>
      <xmax>792</xmax>
      <ymax>376</ymax>
    </bndbox>
  </object>
  <object>
    <name>pedestrian</name>
    <bndbox>
      <xmin>367</xmin>
      <ymin>74</ymin>
      <xmax>397</xmax>
      <ymax>158</ymax>
    </bndbox>
  </object>
  <object>
    <name>pedestrian</name>
    <bndbox>
      <xmin>758</xmin>
      <ymin>267</ymin>
      <xmax>808</xmax>
      <ymax>403</ymax>
    </bndbox>
  </object>
  <object>
    <name>pedestrian</name>
    <bndbox>
      <xmin>400</xmin>
      <ymin>18</ymin>
      <xmax>425</xmax>
      <ymax>86</ymax>
    </bndbox>
  </object>
  <object>
    <name>pedestrian</name>
    <bndbox>
      <xmin>785</xmin>
      <ymin>349</ymin>
      <xmax>844</xmax>
      <ymax>508</ymax>
    </bndbox>
  </object>
  <object>
    <name>pedestrian</name>
    <bndbox>
      <xmin>829</xmin>
      <ymin>353</ymin>
      <xmax>891</xmax>
      <ymax>515</ymax>
    </bndbox>
  </object>
  <object>
    <name>pedestrian</name>
    <bndbox>
      <xmin>507</xmin>
      <ymin>10</ymin>
      <xmax>531</xmax>
      <ymax>76</ymax>
    </bndbox>
  </object>
  <object>
    <name>pedestrian</name>
    <bndbox>
      <xmin>899</xmin>
      <ymin>101</ymin>
      <xmax>944</xmax>
      <ymax>197</ymax>
    </bndbox>
  </object>
  <object>
    <name>pedestrian</name>
    <bndbox>
      <xmin>876</xmin>
      <ymin>268</ymin>
      <xmax>933</xmax>
      <ymax>406</ymax>
    </bndbox>
  </object>
</annotation>
