<annotation>
  <filename>3951.jpg</filename>
  <size>
    <width>960</width>
    <height>540</height>
    <depth>3</depth>
  </size>
  <object>
    <name>pedestrian</name>
    <bndbox>
      <xmin>359</xmin>
      <ymin>69</ymin>
      <xmax>389</xmax>
      <ymax>151</ymax>
    </bndbox>
  </object>
  <object>
    <name>pedestrian</name>
    <bndbox>
      <xmin>87</xmin>
      <ymin>132</ymin>
      <xmax>131</xmax>
      <ymax>229</ymax>
    </bndbox>
  </object>
  <object>
    <name>pedestrian</name>
    <bndbox>
      <xmin>287</xmin>
      <ymin>90</ymin>
      <xmax>319</xmax>
      <ymax>177</ymax>
    </bndbox>
  </object>
  <object>
    <name>pedestrian</name>
    <bndbox>
      <xmin>693</xmin>
      <ymin>176</ymin>
      <xmax>731</xmax>
      <ymax>289</ymax>
    </bndbox>
  </object>
  <object>
    <name>pedestrian</name>
    <bndbox>
      <xmin>883</xmin>
      <ymin>179</ymin>
      <xmax>932</xmax>
      <ymax>294</ymax>
    </bndbox>
  </object>
  <object>
    <name>pedestrian</name>
    <bndbox>
      <xmin>738</xmin>
      <ymin>182</ymin>
      <xmax>778</xmax>
      <ymax>296</ymax>
    </bndbox>
  </object>
  <object>
    <name>pedestrian</name>
    <bndbox>
      <xmin>805</xmin>
      <ymin>190</ymin>
      <xmax>850</xmax>
      <ymax>307</ymax>
    </bndbox>
  </object>
  <object>
    <name>pedestrian</name>
    <bndbox>
      <xmin>380</xmin>
      <ymin>267</ymin>
      <xmax>427</xmax>
      <ymax>402</ymax>
    </bndbox>
  </object>
  <object>
    <name>pedestrian</name>
    <bndbox>
      <xmin>514</xmin>
      <ymin>11</ymin>
      <xmax>537</xmax>
      <ymax>78</ymax>
    </bndbox>
  </object>
  <object>
    <name>pedestrian</name>
    <bndbox>
      <xmin>841</xmin>
      <ymin>192</ymin>
      <xmax>888</xmax>
      <ymax>310</ymax>
    </bndbox>
  </object>
  <object>
    <name>pedestrian</name>
    <bndbox>
      <xmin>553</xmin>
      <ymin>8</ymin>
      <xmax>576</xmax>
      <ymax>74</ymax>
    </bndbox>
  </object>
  <object>
    <name>pedestrian</name>
    <bndbox>
      <xmin>505</xmin>
      <ymin>4</ymin>
      <xmax>528</xmax>
      <ymax>68</ymax>
    </bndbox>
  </object>
</annotation>
