<annotation>
  <filename>3958.jpg</filename>
  <size>
    <width>960</width>
    <height>540</height>
    <depth>3</depth>
  </size>
  <object>
    <name>pedestrian</name>
    <bndbox>
      <xmin>359</xmin>
      <ymin>69</ymin>
      <xmax>388</xmax>
      <ymax>151</ymax>
    </bndbox>
  </object>
  <object>
    <name>pedestrian</name>
    <bndbox>
      <xmin>69</xmin>
      <ymin>137</ymin>
      <xmax>115</xmax>
      <ymax>236</ymax>
    </bndbox>
  </object>
  <object>
    <name>pedestrian</name>
    <bndbox>
      <xmin>278</xmin>
      <ymin>96</ymin>
      <xmax>311</xmax>
      <ymax>184</ymax>
    </bndbox>
  </object>
  <object>
    <name>pedestrian</name>
    <bndbox>
      <xmin>687</xmin>
      <ymin>177</ymin>
      <xmax>726</xmax>
      <ymax>290</ymax>
    </bndbox>
  </object>
  <object>
    <name>pedestrian</name>
    <bndbox>
      <xmin>738</xmin>
      <ymin>186</ymin>
      <xmax>778</xmax>
      <ymax>300</ymax>
    </bndbox>
  </object>
  <object>
    <name>pedestrian</name>
    <bndbox>
      <xmin>797</xmin>
      <ymin>197</ymin>
      <xmax>841</xmax>
      <ymax>314</ymax>
    </bndbox>
  </object>
  <object>
    <name>pedestrian</name>
    <bndbox>
      <xmin>399</xmin>
      <ymin>259</ymin>
      <xmax>445</xmax>
      <ymax>393</ymax>
    </bndbox>
  </object>
  <object>
    <name>pedestrian</name>
    <bndbox>
      <xmin>505</xmin>
      <ymin>15</ymin>
      <xmax>529</xmax>
      <ymax>82</ymax>
    </bndbox>
  </object>
  <object>
    <name>pedestrian</name>
    <bndbox>
      <xmin>835</xmin>
      <ymin>199</ymin>
      <xmax>883</xmax>
      <ymax>318</ymax>
    </bndbox>
  </object>
  <object>
    <name>pedestrian</name>
    <bndbox>
      <xmin>547</xmin>
      <ymin>11</ymin>
      <xmax>570</xmax>
      <ymax>78</ymax>
    </bndbox>
  </object>
  <object>
    <name>pedestrian</name>
    <bndbox>
      <xmin>500</xmin>
      <ymin>4</ymin>
      <xmax>523</xmax>
      <ymax>69</ymax>
    </bndbox>
  </object>
  <object>
    <name>pedestrian</name>
    <bndbox>
      <xmin>-19</xmin>
      <ymin>219</ymin>
      <xmax>44</xmax>
      <ymax>340</ymax>
    </bndbox>
  </object>
  <object>
    <name>pedestrian</name>
    <bndbox>
      <xmin>-25</xmin>
      <ymin>337</ymin>
      <xmax>49</xmax>
      <ymax>492</ymax>
    </bndbox>
  </object>
</annotation>
