<annotation>
  <filename>4371.jpg</filename>
  <size>
    <width>960</width>
    <height>540</height>
    <depth>3</depth>
  </size>
  <object>
    <name>pedestrian</name>
    <bndbox>
      <xmin>488</xmin>
      <ymin>26</ymin>
      <xmax>513</xmax>
      <ymax>97</ymax>
    </bndbox>
  </object>
  <object>
    <name>pedestrian</name>
    <bndbox>
      <xmin>566</xmin>
      <ymin>203</ymin>
      <xmax>604</xmax>
      <ymax>324</ymax>
    </bndbox>
  </object>
  <object>
    <name>pedestrian</name>
    <bndbox>
      <xmin>614</xmin>
      <ymin>5</ymin>
      <xmax>636</xmax>
      <ymax>71</ymax>
    </bndbox>
  </object>
  <object>
    <name>pedestrian</name>
    <bndbox>
      <xmin>138</xmin>
      <ymin>235</ymin>
      <xmax>189</xmax>
      <ymax>359</ymax>
    </bndbox>
  </object>
  <object>
    <name>pedestrian</name>
    <bndbox>
      <xmin>519</xmin>
      <ymin>89</ymin>
      <xmax>549</xmax>
      <ymax>178</ymax>
    </bndbox>
  </object>
  <object>
    <name>pedestrian</name>
    <bndbox>
      <xmin>67</xmin>
      <ymin>139</ymin>
      <xmax>114</xmax>
      <ymax>238</ymax>
    </bndbox>
  </object>
  <object>
    <name>pedestrian</name>
    <bndbox>
      <xmin>423</xmin>
      <ymin>37</ymin>
      <xmax>450</xmax>
      <ymax>110</ymax>
    </bndbox>
  </object>
  <object>
    <name>pedestrian</name>
    <bndbox>
      <xmin>699</xmin>
      <ymin>304</ymin>
      <xmax>750</xmax>
      <ymax>449</ymax>
    </bndbox>
  </object>
  <object>
    <name>pedestrian</name>
    <bndbox>
      <xmin>851</xmin>
      <ymin>143</ymin>
      <xmax>895</xmax>
      <ymax>248</ymax>
    </bndbox>
  </object>
  <object>
    <name>pedestrian</name>
    <bndbox>
      <xmin>302</xmin>
      <ymin>93</ymin>
      <xmax>334</xmax>
      <ymax>181</ymax>
    </bndbox>
  </object>
  <object>
    <name>pedestrian</name>
    <bndbox>
      <xmin>315</xmin>
      <ymin>79</ymin>
      <xmax>346</xmax>
      <ymax>163</ymax>
    </bndbox>
  </object>
  <object>
    <name>pedestrian</name>
    <bndbox>
      <xmin>208</xmin>
      <ymin>136</ymin>
      <xmax>247</xmax>
      <ymax>235</ymax>
    </bndbox>
  </object>
  <object>
    <name>pedestrian</name>
    <bndbox>
      <xmin>554</xmin>
      <ymin>42</ymin>
      <xmax>580</xmax>
      <ymax>117</ymax>
    </bndbox>
  </object>
  <object>
    <name>pedestrian</name>
    <bndbox>
      <xmin>144</xmin>
      <ymin>161</ymin>
      <xmax>188</xmax>
      <ymax>266</ymax>
    </bndbox>
  </object>
  <object>
    <name>pedestrian</name>
    <bndbox>
      <xmin>67</xmin>
      <ymin>168</ymin>
      <xmax>117</xmax>
      <ymax>275</ymax>
    </bndbox>
  </object>
</annotation>
