<annotation>
  <filename>4460.jpg</filename>
  <size>
    <width>960</width>
    <height>540</height>
    <depth>3</depth>
  </size>
  <object>
    <name>pedestrian</name>
    <bndbox>
      <xmin>575</xmin>
      <ymin>203</ymin>
      <xmax>613</xmax>
      <ymax>324</ymax>
    </bndbox>
  </object>
  <object>
    <name>pedestrian</name>
    <bndbox>
      <xmin>597</xmin>
      <ymin>47</ymin>
      <xmax>623</xmax>
      <ymax>124</ymax>
    </bndbox>
  </object>
  <object>
    <name>pedestrian</name>
    <bndbox>
      <xmin>506</xmin>
      <ymin>2</ymin>
      <xmax>529</xmax>
      <ymax>66</ymax>
    </bndbox>
  </object>
  <object>
    <name>pedestrian</name>
    <bndbox>
      <xmin>510</xmin>
      <ymin>474</ymin>
      <xmax>569</xmax>
      <ymax>661</ymax>
    </bndbox>
  </object>
  <object>
    <name>pedestrian</name>
    <bndbox>
      <xmin>909</xmin>
      <ymin>96</ymin>
      <xmax>955</xmax>
      <ymax>191</ymax>
    </bndbox>
  </object>
  <object>
    <name>pedestrian</name>
    <bndbox>
      <xmin>438</xmin>
      <ymin>47</ymin>
      <xmax>465</xmax>
      <ymax>124</ymax>
    </bndbox>
  </object>
  <object>
    <name>pedestrian</name>
    <bndbox>
      <xmin>429</xmin>
      <ymin>32</ymin>
      <xmax>456</xmax>
      <ymax>104</ymax>
    </bndbox>
  </object>
  <object>
    <name>pedestrian</name>
    <bndbox>
      <xmin>340</xmin>
      <ymin>79</ymin>
      <xmax>371</xmax>
      <ymax>163</ymax>
    </bndbox>
  </object>
  <object>
    <name>pedestrian</name>
    <bndbox>
      <xmin>452</xmin>
      <ymin>93</ymin>
      <xmax>483</xmax>
      <ymax>183</ymax>
    </bndbox>
  </object>
  <object>
    <name>pedestrian</name>
    <bndbox>
      <xmin>282</xmin>
      <ymin>96</ymin>
      <xmax>316</xmax>
      <ymax>185</ymax>
    </bndbox>
  </object>
  <object>
    <name>pedestrian</name>
    <bndbox>
      <xmin>242</xmin>
      <ymin>84</ymin>
      <xmax>275</xmax>
      <ymax>169</ymax>
    </bndbox>
  </object>
  <object>
    <name>pedestrian</name>
    <bndbox>
      <xmin>168</xmin>
      <ymin>157</ymin>
      <xmax>210</xmax>
      <ymax>261</ymax>
    </bndbox>
  </object>
  <object>
    <name>pedestrian</name>
    <bndbox>
      <xmin>720</xmin>
      <ymin>325</ymin>
      <xmax>773</xmax>
      <ymax>475</ymax>
    </bndbox>
  </object>
  <object>
    <name>pedestrian</name>
    <bndbox>
      <xmin>486</xmin>
      <ymin>333</ymin>
      <xmax>534</xmax>
      <ymax>485</ymax>
    </bndbox>
  </object>
  <object>
    <name>pedestrian</name>
    <bndbox>
      <xmin>105</xmin>
      <ymin>233</ymin>
      <xmax>158</xmax>
      <ymax>357</ymax>
    </bndbox>
  </object>
</annotation>
