[{"bndbox": {"ymax": 154, "xmax": 911, "ymin": 67, "xmin": 872}, "name": "pedestrian"}, {"bndbox": {"ymax": 266, "xmax": 244, "ymin": 160, "xmin": 203}, "name": "pedestrian"}, {"bndbox": {"ymax": 92, "xmax": 495, "ymin": 23, "xmin": 470}, "name": "pedestrian"}, {"bndbox": {"ymax": 137, "xmax": 327, "ymin": 58, "xmin": 298}, "name": "pedestrian"}, {"bndbox": {"ymax": 416, "xmax": 820, "ymin": 277, "xmin": 769}, "name": "pedestrian"}, {"bndbox": {"ymax": 429, "xmax": 863, "ymin": 287, "xmin": 809}, "name": "pedestrian"}, {"bndbox": {"ymax": 224, "xmax": 237, "ymin": 127, "xmin": 199}, "name": "pedestrian"}, {"bndbox": {"ymax": 481, "xmax": 799, "ymin": 329, "xmin": 744}, "name": "pedestrian"}, {"bndbox": {"ymax": 479, "xmax": 878, "ymin": 326, "xmin": 820}, "name": "pedestrian"}, {"bndbox": {"ymax": 225, "xmax": 859, "ymin": 125, "xmin": 819}, "name": "pedestrian"}, {"bndbox": {"ymax": 105, "xmax": 445, "ymin": 33, "xmin": 419}, "name": "pedestrian"}, {"bndbox": {"ymax": 243, "xmax": 924, "ymin": 138, "xmin": 878}, "name": "pedestrian"}, {"bndbox": {"ymax": 82, "xmax": 499, "ymin": 14, "xmin": 475}, "name": "pedestrian"}, {"bndbox": {"ymax": 356, "xmax": 172, "ymin": 232, "xmin": 119}, "name": "pedestrian"}, {"bndbox": {"ymax": 96, "xmax": 867, "ymin": 21, "xmin": 835}, "name": "pedestrian"}, {"bndbox": {"ymax": 350, "xmax": 110, "ymin": 228, "xmin": 54}, "name": "pedestrian"}, {"bndbox": {"ymax": 352, "xmax": 58, "ymin": 229, "xmin": -3}, "name": "pedestrian"}, {"bndbox": {"ymax": 525, "xmax": 902, "ymin": 361, "xmin": 840}, "name": "pedestrian"}]