[{"bndbox": {"ymax": 146, "xmax": 924, "ymin": 60, "xmin": 884}, "name": "pedestrian"}, {"bndbox": {"ymax": 231, "xmax": 114, "ymin": 133, "xmin": 69}, "name": "pedestrian"}, {"bndbox": {"ymax": 271, "xmax": 921, "ymin": 161, "xmin": 874}, "name": "pedestrian"}, {"bndbox": {"ymax": 137, "xmax": 424, "ymin": 58, "xmin": 395}, "name": "pedestrian"}, {"bndbox": {"ymax": 312, "xmax": 900, "ymin": 194, "xmin": 852}, "name": "pedestrian"}, {"bndbox": {"ymax": 406, "xmax": 802, "ymin": 270, "xmin": 753}, "name": "pedestrian"}, {"bndbox": {"ymax": 194, "xmax": 258, "ymin": 104, "xmin": 222}, "name": "pedestrian"}, {"bndbox": {"ymax": 359, "xmax": 807, "ymin": 232, "xmin": 761}, "name": "pedestrian"}, {"bndbox": {"ymax": 161, "xmax": 316, "ymin": 77, "xmin": 284}, "name": "pedestrian"}, {"bndbox": {"ymax": 212, "xmax": 397, "ymin": 116, "xmin": 363}, "name": "pedestrian"}, {"bndbox": {"ymax": 183, "xmax": 864, "ymin": 92, "xmin": 827}, "name": "pedestrian"}, {"bndbox": {"ymax": 218, "xmax": 362, "ymin": 122, "xmin": 327}, "name": "pedestrian"}, {"bndbox": {"ymax": 211, "xmax": 277, "ymin": 117, "xmin": 241}, "name": "pedestrian"}, {"bndbox": {"ymax": 599, "xmax": 289, "ymin": 424, "xmin": 222}, "name": "pedestrian"}, {"bndbox": {"ymax": 199, "xmax": 254, "ymin": 108, "xmin": 218}, "name": "pedestrian"}, {"bndbox": {"ymax": 229, "xmax": 870, "ymin": 128, "xmin": 830}, "name": "pedestrian"}, {"bndbox": {"ymax": 236, "xmax": 904, "ymin": 134, "xmin": 860}, "name": "pedestrian"}, {"bndbox": {"ymax": 234, "xmax": 189, "ymin": 136, "xmin": 148}, "name": "pedestrian"}, {"bndbox": {"ymax": 411, "xmax": 291, "ymin": 275, "xmin": 239}, "name": "pedestrian"}, {"bndbox": {"ymax": 240, "xmax": 266, "ymin": 140, "xmin": 227}, "name": "pedestrian"}, {"bndbox": {"ymax": 205, "xmax": 930, "ymin": 108, "xmin": 886}, "name": "pedestrian"}, {"bndbox": {"ymax": 326, "xmax": 75, "ymin": 208, "xmin": 17}, "name": "pedestrian"}]