[{"bndbox": {"ymax": 135, "xmax": 949, "ymin": 50, "xmin": 907}, "name": "pedestrian"}, {"bndbox": {"ymax": 189, "xmax": 905, "ymin": 96, "xmin": 864}, "name": "pedestrian"}, {"bndbox": {"ymax": 78, "xmax": 555, "ymin": 12, "xmin": 532}, "name": "pedestrian"}, {"bndbox": {"ymax": 211, "xmax": 942, "ymin": 112, "xmin": 896}, "name": "pedestrian"}, {"bndbox": {"ymax": 575, "xmax": 788, "ymin": 403, "xmin": 728}, "name": "pedestrian"}, {"bndbox": {"ymax": 291, "xmax": 60, "ymin": 180, "xmin": 4}, "name": "pedestrian"}, {"bndbox": {"ymax": 127, "xmax": 532, "ymin": 50, "xmin": 505}, "name": "pedestrian"}, {"bndbox": {"ymax": 319, "xmax": 869, "ymin": 200, "xmin": 823}, "name": "pedestrian"}, {"bndbox": {"ymax": 125, "xmax": 496, "ymin": 48, "xmin": 469}, "name": "pedestrian"}, {"bndbox": {"ymax": 126, "xmax": 461, "ymin": 49, "xmin": 434}, "name": "pedestrian"}, {"bndbox": {"ymax": 120, "xmax": 430, "ymin": 45, "xmin": 403}, "name": "pedestrian"}, {"bndbox": {"ymax": 423, "xmax": 752, "ymin": 283, "xmin": 703}, "name": "pedestrian"}, {"bndbox": {"ymax": 435, "xmax": 795, "ymin": 292, "xmin": 744}, "name": "pedestrian"}, {"bndbox": {"ymax": 107, "xmax": 385, "ymin": 35, "xmin": 359}, "name": "pedestrian"}, {"bndbox": {"ymax": 178, "xmax": 555, "ymin": 89, "xmin": 526}, "name": "pedestrian"}, {"bndbox": {"ymax": 169, "xmax": 360, "ymin": 84, "xmin": 328}, "name": "pedestrian"}, {"bndbox": {"ymax": 381, "xmax": 818, "ymin": 249, "xmin": 770}, "name": "pedestrian"}, {"bndbox": {"ymax": 189, "xmax": 273, "ymin": 100, "xmin": 238}, "name": "pedestrian"}, {"bndbox": {"ymax": 355, "xmax": 908, "ymin": 228, "xmin": 856}, "name": "pedestrian"}, {"bndbox": {"ymax": 434, "xmax": 891, "ymin": 290, "xmin": 835}, "name": "pedestrian"}, {"bndbox": {"ymax": 100, "xmax": 599, "ymin": 28, "xmin": 574}, "name": "pedestrian"}, {"bndbox": {"ymax": 244, "xmax": 881, "ymin": 141, "xmin": 839}, "name": "pedestrian"}, {"bndbox": {"ymax": 93, "xmax": 458, "ymin": 23, "xmin": 433}, "name": "pedestrian"}, {"bndbox": {"ymax": 183, "xmax": 924, "ymin": 91, "xmin": 882}, "name": "pedestrian"}, {"bndbox": {"ymax": 533, "xmax": 459, "ymin": 373, "xmin": 404}, "name": "pedestrian"}, {"bndbox": {"ymax": 78, "xmax": 822, "ymin": 8, "xmin": 793}, "name": "pedestrian"}, {"bndbox": {"ymax": 64, "xmax": 528, "ymin": 0, "xmin": 505}, "name": "pedestrian"}]