[{"bndbox": {"ymax": 64, "xmax": 721, "ymin": -1, "xmin": 697}, "name": "pedestrian"}, {"bndbox": {"ymax": 374, "xmax": 197, "ymin": 246, "xmin": 145}, "name": "pedestrian"}, {"bndbox": {"ymax": 142, "xmax": 564, "ymin": 62, "xmin": 537}, "name": "pedestrian"}, {"bndbox": {"ymax": 333, "xmax": 492, "ymin": 211, "xmin": 451}, "name": "pedestrian"}, {"bndbox": {"ymax": 60, "xmax": 750, "ymin": -4, "xmin": 725}, "name": "pedestrian"}, {"bndbox": {"ymax": 125, "xmax": 523, "ymin": 48, "xmin": 497}, "name": "pedestrian"}, {"bndbox": {"ymax": 145, "xmax": 522, "ymin": 63, "xmin": 494}, "name": "pedestrian"}, {"bndbox": {"ymax": 435, "xmax": 778, "ymin": 292, "xmin": 727}, "name": "pedestrian"}, {"bndbox": {"ymax": 101, "xmax": 461, "ymin": 30, "xmin": 436}, "name": "pedestrian"}, {"bndbox": {"ymax": 131, "xmax": 386, "ymin": 54, "xmin": 357}, "name": "pedestrian"}, {"bndbox": {"ymax": 112, "xmax": 422, "ymin": 39, "xmin": 395}, "name": "pedestrian"}, {"bndbox": {"ymax": 223, "xmax": 196, "ymin": 127, "xmin": 155}, "name": "pedestrian"}, {"bndbox": {"ymax": 324, "xmax": 187, "ymin": 207, "xmin": 138}, "name": "pedestrian"}, {"bndbox": {"ymax": 84, "xmax": 812, "ymin": 13, "xmin": 784}, "name": "pedestrian"}, {"bndbox": {"ymax": 288, "xmax": 133, "ymin": 179, "xmin": 84}, "name": "pedestrian"}, {"bndbox": {"ymax": 307, "xmax": 186, "ymin": 193, "xmin": 139}, "name": "pedestrian"}, {"bndbox": {"ymax": 613, "xmax": 233, "ymin": 433, "xmin": 163}, "name": "pedestrian"}, {"bndbox": {"ymax": 656, "xmax": 296, "ymin": 467, "xmin": 226}, "name": "pedestrian"}, {"bndbox": {"ymax": 108, "xmax": 416, "ymin": 35, "xmin": 390}, "name": "pedestrian"}]