[{"bndbox": {"ymax": 60, "xmax": 720, "ymin": -4, "xmin": 697}, "name": "pedestrian"}, {"bndbox": {"ymax": 387, "xmax": 178, "ymin": 257, "xmin": 123}, "name": "pedestrian"}, {"bndbox": {"ymax": 136, "xmax": 567, "ymin": 56, "xmin": 540}, "name": "pedestrian"}, {"bndbox": {"ymax": 343, "xmax": 469, "ymin": 219, "xmin": 427}, "name": "pedestrian"}, {"bndbox": {"ymax": 119, "xmax": 534, "ymin": 43, "xmin": 507}, "name": "pedestrian"}, {"bndbox": {"ymax": 140, "xmax": 531, "ymin": 60, "xmin": 503}, "name": "pedestrian"}, {"bndbox": {"ymax": 456, "xmax": 774, "ymin": 310, "xmin": 722}, "name": "pedestrian"}, {"bndbox": {"ymax": 99, "xmax": 472, "ymin": 28, "xmin": 447}, "name": "pedestrian"}, {"bndbox": {"ymax": 137, "xmax": 374, "ymin": 58, "xmin": 345}, "name": "pedestrian"}, {"bndbox": {"ymax": 117, "xmax": 415, "ymin": 43, "xmin": 388}, "name": "pedestrian"}, {"bndbox": {"ymax": 234, "xmax": 178, "ymin": 136, "xmin": 136}, "name": "pedestrian"}, {"bndbox": {"ymax": 311, "xmax": 207, "ymin": 197, "xmin": 161}, "name": "pedestrian"}, {"bndbox": {"ymax": 88, "xmax": 810, "ymin": 17, "xmin": 781}, "name": "pedestrian"}, {"bndbox": {"ymax": 273, "xmax": 149, "ymin": 166, "xmin": 102}, "name": "pedestrian"}, {"bndbox": {"ymax": 296, "xmax": 214, "ymin": 185, "xmin": 169}, "name": "pedestrian"}, {"bndbox": {"ymax": 582, "xmax": 265, "ymin": 411, "xmin": 199}, "name": "pedestrian"}, {"bndbox": {"ymax": 623, "xmax": 320, "ymin": 443, "xmin": 254}, "name": "pedestrian"}, {"bndbox": {"ymax": 110, "xmax": 403, "ymin": 37, "xmin": 376}, "name": "pedestrian"}, {"bndbox": {"ymax": 283, "xmax": 926, "ymin": 171, "xmin": 877}, "name": "pedestrian"}]