[{"bndbox": {"ymax": 446, "xmax": 95, "ymin": 303, "xmin": 29}, "name": "pedestrian"}, {"bndbox": {"ymax": 117, "xmax": 547, "ymin": 42, "xmin": 521}, "name": "pedestrian"}, {"bndbox": {"ymax": 394, "xmax": 386, "ymin": 260, "xmin": 338}, "name": "pedestrian"}, {"bndbox": {"ymax": 97, "xmax": 575, "ymin": 26, "xmin": 550}, "name": "pedestrian"}, {"bndbox": {"ymax": 118, "xmax": 537, "ymin": 43, "xmin": 511}, "name": "pedestrian"}, {"bndbox": {"ymax": 525, "xmax": 736, "ymin": 365, "xmin": 680}, "name": "pedestrian"}, {"bndbox": {"ymax": 80, "xmax": 484, "ymin": 13, "xmin": 460}, "name": "pedestrian"}, {"bndbox": {"ymax": 152, "xmax": 331, "ymin": 70, "xmin": 300}, "name": "pedestrian"}, {"bndbox": {"ymax": 145, "xmax": 367, "ymin": 65, "xmin": 337}, "name": "pedestrian"}, {"bndbox": {"ymax": 277, "xmax": 106, "ymin": 170, "xmin": 55}, "name": "pedestrian"}, {"bndbox": {"ymax": 276, "xmax": 286, "ymin": 167, "xmin": 245}, "name": "pedestrian"}, {"bndbox": {"ymax": 100, "xmax": 793, "ymin": 27, "xmin": 765}, "name": "pedestrian"}, {"bndbox": {"ymax": 241, "xmax": 210, "ymin": 141, "xmin": 169}, "name": "pedestrian"}, {"bndbox": {"ymax": 255, "xmax": 301, "ymin": 151, "xmin": 262}, "name": "pedestrian"}, {"bndbox": {"ymax": 496, "xmax": 356, "ymin": 343, "xmin": 300}, "name": "pedestrian"}, {"bndbox": {"ymax": 531, "xmax": 409, "ymin": 371, "xmin": 351}, "name": "pedestrian"}, {"bndbox": {"ymax": 131, "xmax": 370, "ymin": 53, "xmin": 341}, "name": "pedestrian"}, {"bndbox": {"ymax": 329, "xmax": 914, "ymin": 207, "xmin": 863}, "name": "pedestrian"}, {"bndbox": {"ymax": 369, "xmax": 111, "ymin": 243, "xmin": 54}, "name": "pedestrian"}, {"bndbox": {"ymax": 319, "xmax": 78, "ymin": 202, "xmin": 22}, "name": "pedestrian"}]