[{"bndbox": {"ymax": 425, "xmax": 326, "ymin": 286, "xmin": 273}, "name": "pedestrian"}, {"bndbox": {"ymax": 84, "xmax": 593, "ymin": 16, "xmin": 569}, "name": "pedestrian"}, {"bndbox": {"ymax": 104, "xmax": 556, "ymin": 32, "xmin": 531}, "name": "pedestrian"}, {"bndbox": {"ymax": 572, "xmax": 715, "ymin": 402, "xmin": 657}, "name": "pedestrian"}, {"bndbox": {"ymax": 65, "xmax": 496, "ymin": 2, "xmin": 473}, "name": "pedestrian"}, {"bndbox": {"ymax": 165, "xmax": 302, "ymin": 80, "xmin": 269}, "name": "pedestrian"}, {"bndbox": {"ymax": 160, "xmax": 334, "ymin": 76, "xmin": 303}, "name": "pedestrian"}, {"bndbox": {"ymax": 309, "xmax": 58, "ymin": 194, "xmin": 0}, "name": "pedestrian"}, {"bndbox": {"ymax": 251, "xmax": 321, "ymin": 148, "xmin": 283}, "name": "pedestrian"}, {"bndbox": {"ymax": 111, "xmax": 779, "ymin": 36, "xmin": 750}, "name": "pedestrian"}, {"bndbox": {"ymax": 226, "xmax": 248, "ymin": 129, "xmin": 210}, "name": "pedestrian"}, {"bndbox": {"ymax": 235, "xmax": 348, "ymin": 135, "xmin": 312}, "name": "pedestrian"}, {"bndbox": {"ymax": 458, "xmax": 403, "ymin": 312, "xmin": 351}, "name": "pedestrian"}, {"bndbox": {"ymax": 482, "xmax": 454, "ymin": 331, "xmin": 402}, "name": "pedestrian"}, {"bndbox": {"ymax": 144, "xmax": 346, "ymin": 64, "xmin": 316}, "name": "pedestrian"}, {"bndbox": {"ymax": 361, "xmax": 908, "ymin": 233, "xmin": 856}, "name": "pedestrian"}, {"bndbox": {"ymax": 339, "xmax": 157, "ymin": 219, "xmin": 105}, "name": "pedestrian"}, {"bndbox": {"ymax": 290, "xmax": 123, "ymin": 180, "xmin": 73}, "name": "pedestrian"}]