[{"bndbox": {"ymax": 99, "xmax": 554, "ymin": 28, "xmin": 529}, "name": "pedestrian"}, {"bndbox": {"ymax": 265, "xmax": 684, "ymin": 157, "xmin": 649}, "name": "pedestrian"}, {"bndbox": {"ymax": 103, "xmax": 464, "ymin": 31, "xmin": 438}, "name": "pedestrian"}, {"bndbox": {"ymax": 92, "xmax": 570, "ymin": 22, "xmin": 546}, "name": "pedestrian"}, {"bndbox": {"ymax": 190, "xmax": 613, "ymin": 98, "xmin": 583}, "name": "pedestrian"}, {"bndbox": {"ymax": 199, "xmax": 650, "ymin": 106, "xmin": 620}, "name": "pedestrian"}, {"bndbox": {"ymax": 144, "xmax": 503, "ymin": 63, "xmin": 474}, "name": "pedestrian"}, {"bndbox": {"ymax": 165, "xmax": 727, "ymin": 79, "xmin": 697}, "name": "pedestrian"}, {"bndbox": {"ymax": 183, "xmax": 883, "ymin": 92, "xmin": 844}, "name": "pedestrian"}, {"bndbox": {"ymax": 120, "xmax": 405, "ymin": 45, "xmin": 377}, "name": "pedestrian"}, {"bndbox": {"ymax": 303, "xmax": 40, "ymin": 189, "xmin": -19}, "name": "pedestrian"}, {"bndbox": {"ymax": 277, "xmax": 244, "ymin": 169, "xmin": 202}, "name": "pedestrian"}, {"bndbox": {"ymax": 392, "xmax": 267, "ymin": 260, "xmin": 216}, "name": "pedestrian"}]