[{"bndbox": {"ymax": 96, "xmax": 558, "ymin": 25, "xmin": 534}, "name": "pedestrian"}, {"bndbox": {"ymax": 271, "xmax": 683, "ymin": 162, "xmin": 648}, "name": "pedestrian"}, {"bndbox": {"ymax": 98, "xmax": 470, "ymin": 27, "xmin": 444}, "name": "pedestrian"}, {"bndbox": {"ymax": 86, "xmax": 574, "ymin": 17, "xmin": 550}, "name": "pedestrian"}, {"bndbox": {"ymax": 187, "xmax": 618, "ymin": 96, "xmin": 588}, "name": "pedestrian"}, {"bndbox": {"ymax": 195, "xmax": 655, "ymin": 103, "xmin": 625}, "name": "pedestrian"}, {"bndbox": {"ymax": 141, "xmax": 511, "ymin": 61, "xmin": 483}, "name": "pedestrian"}, {"bndbox": {"ymax": 168, "xmax": 723, "ymin": 81, "xmin": 693}, "name": "pedestrian"}, {"bndbox": {"ymax": 178, "xmax": 876, "ymin": 88, "xmin": 838}, "name": "pedestrian"}, {"bndbox": {"ymax": 118, "xmax": 408, "ymin": 43, "xmin": 381}, "name": "pedestrian"}, {"bndbox": {"ymax": 269, "xmax": 260, "ymin": 163, "xmin": 219}, "name": "pedestrian"}, {"bndbox": {"ymax": 383, "xmax": 288, "ymin": 252, "xmin": 238}, "name": "pedestrian"}, {"bndbox": {"ymax": 72, "xmax": 870, "ymin": 2, "xmin": 839}, "name": "pedestrian"}]