[{"bndbox": {"ymax": 69, "xmax": 701, "ymin": 3, "xmin": 677}, "name": "pedestrian"}, {"bndbox": {"ymax": 427, "xmax": 79, "ymin": 288, "xmin": 13}, "name": "pedestrian"}, {"bndbox": {"ymax": 427, "xmax": 123, "ymin": 288, "xmin": 61}, "name": "pedestrian"}, {"bndbox": {"ymax": 512, "xmax": 419, "ymin": 356, "xmin": 363}, "name": "pedestrian"}, {"bndbox": {"ymax": 519, "xmax": 466, "ymin": 361, "xmin": 412}, "name": "pedestrian"}, {"bndbox": {"ymax": 320, "xmax": 712, "ymin": 201, "xmin": 671}, "name": "pedestrian"}, {"bndbox": {"ymax": 365, "xmax": 484, "ymin": 237, "xmin": 441}, "name": "pedestrian"}, {"bndbox": {"ymax": 457, "xmax": 824, "ymin": 309, "xmin": 770}, "name": "pedestrian"}, {"bndbox": {"ymax": 242, "xmax": 348, "ymin": 140, "xmin": 311}, "name": "pedestrian"}, {"bndbox": {"ymax": 225, "xmax": 860, "ymin": 126, "xmin": 820}, "name": "pedestrian"}, {"bndbox": {"ymax": 307, "xmax": 848, "ymin": 191, "xmin": 804}, "name": "pedestrian"}, {"bndbox": {"ymax": 498, "xmax": 792, "ymin": 342, "xmin": 736}, "name": "pedestrian"}, {"bndbox": {"ymax": 410, "xmax": 817, "ymin": 273, "xmin": 767}, "name": "pedestrian"}, {"bndbox": {"ymax": 203, "xmax": 278, "ymin": 111, "xmin": 242}, "name": "pedestrian"}, {"bndbox": {"ymax": 462, "xmax": 905, "ymin": 312, "xmin": 847}, "name": "pedestrian"}]