[{"bndbox": {"ymax": 282, "xmax": 742, "ymin": 171, "xmin": 704}, "name": "pedestrian"}, {"bndbox": {"ymax": 515, "xmax": 332, "ymin": 358, "xmin": 273}, "name": "pedestrian"}, {"bndbox": {"ymax": 618, "xmax": 793, "ymin": 435, "xmin": 730}, "name": "pedestrian"}, {"bndbox": {"ymax": 326, "xmax": 195, "ymin": 208, "xmin": 146}, "name": "pedestrian"}, {"bndbox": {"ymax": 168, "xmax": 901, "ymin": 79, "xmin": 862}, "name": "pedestrian"}, {"bndbox": {"ymax": 360, "xmax": 674, "ymin": 232, "xmin": 632}, "name": "pedestrian"}, {"bndbox": {"ymax": 584, "xmax": 692, "ymin": 412, "xmin": 634}, "name": "pedestrian"}, {"bndbox": {"ymax": 145, "xmax": 377, "ymin": 65, "xmin": 348}, "name": "pedestrian"}, {"bndbox": {"ymax": 627, "xmax": 868, "ymin": 437, "xmin": 803}, "name": "pedestrian"}]