[{"bndbox": {"ymax": 257, "xmax": 746, "ymin": 151, "xmin": 710}, "name": "pedestrian"}, {"bndbox": {"ymax": 671, "xmax": 184, "ymin": 472, "xmin": 109}, "name": "pedestrian"}, {"bndbox": {"ymax": 135, "xmax": 881, "ymin": 53, "xmin": 845}, "name": "pedestrian"}, {"bndbox": {"ymax": 390, "xmax": 524, "ymin": 256, "xmin": 481}, "name": "pedestrian"}, {"bndbox": {"ymax": 121, "xmax": 435, "ymin": 45, "xmin": 408}, "name": "pedestrian"}, {"bndbox": {"ymax": 68, "xmax": 647, "ymin": 3, "xmin": 625}, "name": "pedestrian"}]