[{"bndbox": {"ymax": 207, "xmax": 750, "ymin": 112, "xmin": 717}, "name": "pedestrian"}, {"bndbox": {"ymax": 82, "xmax": 867, "ymin": 10, "xmin": 835}, "name": "pedestrian"}, {"bndbox": {"ymax": 507, "xmax": 71, "ymin": 348, "xmin": -1}, "name": "pedestrian"}, {"bndbox": {"ymax": 62, "xmax": 552, "ymin": -1, "xmin": 530}, "name": "pedestrian"}, {"bndbox": {"ymax": 120, "xmax": 591, "ymin": 44, "xmin": 566}, "name": "pedestrian"}, {"bndbox": {"ymax": 218, "xmax": 242, "ymin": 122, "xmin": 204}, "name": "pedestrian"}, {"bndbox": {"ymax": 520, "xmax": 752, "ymin": 361, "xmin": 696}, "name": "pedestrian"}, {"bndbox": {"ymax": 435, "xmax": 907, "ymin": 291, "xmin": 850}, "name": "pedestrian"}]