[{"bndbox": {"ymax": 191, "xmax": 742, "ymin": 99, "xmin": 710}, "name": "pedestrian"}, {"bndbox": {"ymax": 207, "xmax": 227, "ymin": 114, "xmin": 189}, "name": "pedestrian"}, {"bndbox": {"ymax": 186, "xmax": 308, "ymin": 97, "xmin": 274}, "name": "pedestrian"}, {"bndbox": {"ymax": 418, "xmax": 893, "ymin": 278, "xmin": 838}, "name": "pedestrian"}, {"bndbox": {"ymax": 210, "xmax": 264, "ymin": 116, "xmin": 228}, "name": "pedestrian"}, {"bndbox": {"ymax": 84, "xmax": 667, "ymin": 15, "xmin": 643}, "name": "pedestrian"}, {"bndbox": {"ymax": 469, "xmax": 699, "ymin": 320, "xmin": 648}, "name": "pedestrian"}, {"bndbox": {"ymax": 327, "xmax": 178, "ymin": 209, "xmin": 128}, "name": "pedestrian"}, {"bndbox": {"ymax": 263, "xmax": 917, "ymin": 155, "xmin": 871}, "name": "pedestrian"}, {"bndbox": {"ymax": 202, "xmax": 931, "ymin": 105, "xmin": 887}, "name": "pedestrian"}, {"bndbox": {"ymax": 428, "xmax": 185, "ymin": 289, "xmin": 127}, "name": "pedestrian"}, {"bndbox": {"ymax": 627, "xmax": 769, "ymin": 442, "xmin": 706}, "name": "pedestrian"}, {"bndbox": {"ymax": 568, "xmax": 58, "ymin": 394, "xmin": -20}, "name": "pedestrian"}]