[{"bndbox": {"ymax": 166, "xmax": 791, "ymin": 79, "xmin": 759}, "name": "pedestrian"}, {"bndbox": {"ymax": 211, "xmax": 509, "ymin": 115, "xmin": 477}, "name": "pedestrian"}, {"bndbox": {"ymax": 139, "xmax": 396, "ymin": 60, "xmin": 367}, "name": "pedestrian"}, {"bndbox": {"ymax": 306, "xmax": 816, "ymin": 190, "xmin": 773}, "name": "pedestrian"}, {"bndbox": {"ymax": 115, "xmax": 387, "ymin": 41, "xmin": 360}, "name": "pedestrian"}, {"bndbox": {"ymax": 100, "xmax": 550, "ymin": 28, "xmin": 525}, "name": "pedestrian"}, {"bndbox": {"ymax": 93, "xmax": 529, "ymin": 23, "xmin": 505}, "name": "pedestrian"}, {"bndbox": {"ymax": 199, "xmax": 932, "ymin": 103, "xmin": 888}, "name": "pedestrian"}]