[{"bndbox": {"ymax": 140, "xmax": 821, "ymin": 58, "xmin": 789}, "name": "pedestrian"}, {"bndbox": {"ymax": 312, "xmax": 394, "ymin": 195, "xmin": 352}, "name": "pedestrian"}, {"bndbox": {"ymax": 138, "xmax": 404, "ymin": 59, "xmin": 375}, "name": "pedestrian"}, {"bndbox": {"ymax": 212, "xmax": 866, "ymin": 115, "xmin": 827}, "name": "pedestrian"}, {"bndbox": {"ymax": 190, "xmax": 277, "ymin": 100, "xmin": 242}, "name": "pedestrian"}, {"bndbox": {"ymax": 145, "xmax": 424, "ymin": 64, "xmin": 395}, "name": "pedestrian"}, {"bndbox": {"ymax": 102, "xmax": 508, "ymin": 30, "xmin": 482}, "name": "pedestrian"}, {"bndbox": {"ymax": 271, "xmax": 897, "ymin": 161, "xmin": 852}, "name": "pedestrian"}, {"bndbox": {"ymax": 100, "xmax": 457, "ymin": 29, "xmin": 432}, "name": "pedestrian"}, {"bndbox": {"ymax": 102, "xmax": 429, "ymin": 31, "xmin": 403}, "name": "pedestrian"}, {"bndbox": {"ymax": 254, "xmax": 952, "ymin": 147, "xmin": 902}, "name": "pedestrian"}, {"bndbox": {"ymax": 76, "xmax": 477, "ymin": 10, "xmin": 453}, "name": "pedestrian"}, {"bndbox": {"ymax": 443, "xmax": 549, "ymin": 299, "xmin": 504}, "name": "pedestrian"}, {"bndbox": {"ymax": 72, "xmax": 525, "ymin": 7, "xmin": 502}, "name": "pedestrian"}, {"bndbox": {"ymax": 89, "xmax": 493, "ymin": 20, "xmin": 468}, "name": "pedestrian"}, {"bndbox": {"ymax": 70, "xmax": 499, "ymin": 5, "xmin": 476}, "name": "pedestrian"}, {"bndbox": {"ymax": 282, "xmax": 113, "ymin": 173, "xmin": 63}, "name": "pedestrian"}, {"bndbox": {"ymax": 659, "xmax": 404, "ymin": 472, "xmin": 338}, "name": "pedestrian"}]