[{"bndbox": {"ymax": 96, "xmax": 861, "ymin": 22, "xmin": 829}, "name": "pedestrian"}, {"bndbox": {"ymax": 320, "xmax": 113, "ymin": 203, "xmin": 59}, "name": "pedestrian"}, {"bndbox": {"ymax": 106, "xmax": 874, "ymin": 30, "xmin": 840}, "name": "pedestrian"}, {"bndbox": {"ymax": 321, "xmax": 149, "ymin": 205, "xmin": 99}, "name": "pedestrian"}, {"bndbox": {"ymax": 519, "xmax": 756, "ymin": 359, "xmin": 700}, "name": "pedestrian"}, {"bndbox": {"ymax": 249, "xmax": 194, "ymin": 148, "xmin": 152}, "name": "pedestrian"}, {"bndbox": {"ymax": 252, "xmax": 160, "ymin": 150, "xmin": 116}, "name": "pedestrian"}, {"bndbox": {"ymax": 161, "xmax": 329, "ymin": 78, "xmin": 297}, "name": "pedestrian"}, {"bndbox": {"ymax": 77, "xmax": 808, "ymin": 8, "xmin": 780}, "name": "pedestrian"}, {"bndbox": {"ymax": 174, "xmax": 347, "ymin": 87, "xmin": 315}, "name": "pedestrian"}, {"bndbox": {"ymax": 291, "xmax": 691, "ymin": 178, "xmin": 654}, "name": "pedestrian"}, {"bndbox": {"ymax": 198, "xmax": 241, "ymin": 107, "xmin": 204}, "name": "pedestrian"}, {"bndbox": {"ymax": 543, "xmax": 843, "ymin": 376, "xmin": 782}, "name": "pedestrian"}, {"bndbox": {"ymax": 133, "xmax": 727, "ymin": 54, "xmin": 699}, "name": "pedestrian"}, {"bndbox": {"ymax": 333, "xmax": 367, "ymin": 212, "xmin": 324}, "name": "pedestrian"}, {"bndbox": {"ymax": 336, "xmax": 406, "ymin": 214, "xmin": 363}, "name": "pedestrian"}, {"bndbox": {"ymax": 155, "xmax": 316, "ymin": 73, "xmin": 285}, "name": "pedestrian"}, {"bndbox": {"ymax": 493, "xmax": 487, "ymin": 340, "xmin": 436}, "name": "pedestrian"}, {"bndbox": {"ymax": 265, "xmax": 116, "ymin": 160, "xmin": 67}, "name": "pedestrian"}, {"bndbox": {"ymax": 247, "xmax": 97, "ymin": 146, "xmin": 49}, "name": "pedestrian"}, {"bndbox": {"ymax": 76, "xmax": 506, "ymin": 10, "xmin": 482}, "name": "pedestrian"}, {"bndbox": {"ymax": 79, "xmax": 954, "ymin": 4, "xmin": 915}, "name": "pedestrian"}, {"bndbox": {"ymax": 131, "xmax": 342, "ymin": 54, "xmin": 313}, "name": "pedestrian"}]