[{"bndbox": {"ymax": 76, "xmax": 822, "ymin": 6, "xmin": 793}, "name": "pedestrian"}, {"bndbox": {"ymax": 84, "xmax": 889, "ymin": 11, "xmin": 856}, "name": "pedestrian"}, {"bndbox": {"ymax": 682, "xmax": 681, "ymin": 486, "xmin": 619}, "name": "pedestrian"}, {"bndbox": {"ymax": 349, "xmax": 49, "ymin": 226, "xmin": -13}, "name": "pedestrian"}, {"bndbox": {"ymax": 200, "xmax": 252, "ymin": 109, "xmin": 216}, "name": "pedestrian"}, {"bndbox": {"ymax": 215, "xmax": 270, "ymin": 120, "xmin": 233}, "name": "pedestrian"}, {"bndbox": {"ymax": 216, "xmax": 742, "ymin": 119, "xmin": 708}, "name": "pedestrian"}, {"bndbox": {"ymax": 257, "xmax": 148, "ymin": 154, "xmin": 102}, "name": "pedestrian"}, {"bndbox": {"ymax": 716, "xmax": 763, "ymin": 505, "xmin": 698}, "name": "pedestrian"}, {"bndbox": {"ymax": 182, "xmax": 688, "ymin": 93, "xmin": 658}, "name": "pedestrian"}, {"bndbox": {"ymax": 242, "xmax": 412, "ymin": 140, "xmin": 376}, "name": "pedestrian"}, {"bndbox": {"ymax": 247, "xmax": 444, "ymin": 144, "xmin": 408}, "name": "pedestrian"}, {"bndbox": {"ymax": 350, "xmax": 610, "ymin": 224, "xmin": 571}, "name": "pedestrian"}, {"bndbox": {"ymax": 217, "xmax": 191, "ymin": 122, "xmin": 151}, "name": "pedestrian"}, {"bndbox": {"ymax": 201, "xmax": 171, "ymin": 110, "xmin": 132}, "name": "pedestrian"}, {"bndbox": {"ymax": 111, "xmax": 441, "ymin": 38, "xmin": 415}, "name": "pedestrian"}, {"bndbox": {"ymax": 94, "xmax": 438, "ymin": 25, "xmin": 413}, "name": "pedestrian"}, {"bndbox": {"ymax": 197, "xmax": 280, "ymin": 105, "xmin": 245}, "name": "pedestrian"}]