[{"bndbox": {"ymax": 157, "xmax": 774, "ymin": 73, "xmin": 743}, "name": "pedestrian"}, {"bndbox": {"ymax": 249, "xmax": 134, "ymin": 147, "xmin": 88}, "name": "pedestrian"}, {"bndbox": {"ymax": 152, "xmax": 370, "ymin": 70, "xmin": 340}, "name": "pedestrian"}, {"bndbox": {"ymax": 355, "xmax": 933, "ymin": 228, "xmin": 879}, "name": "pedestrian"}, {"bndbox": {"ymax": 178, "xmax": 336, "ymin": 90, "xmin": 303}, "name": "pedestrian"}, {"bndbox": {"ymax": 104, "xmax": 627, "ymin": 31, "xmin": 603}, "name": "pedestrian"}, {"bndbox": {"ymax": 354, "xmax": 763, "ymin": 228, "xmin": 719}, "name": "pedestrian"}, {"bndbox": {"ymax": 265, "xmax": 238, "ymin": 160, "xmin": 196}, "name": "pedestrian"}, {"bndbox": {"ymax": 309, "xmax": 888, "ymin": 192, "xmin": 841}, "name": "pedestrian"}, {"bndbox": {"ymax": 240, "xmax": 908, "ymin": 137, "xmin": 863}, "name": "pedestrian"}, {"bndbox": {"ymax": 364, "xmax": 323, "ymin": 237, "xmin": 276}, "name": "pedestrian"}, {"bndbox": {"ymax": 502, "xmax": 850, "ymin": 344, "xmin": 792}, "name": "pedestrian"}, {"bndbox": {"ymax": 455, "xmax": 192, "ymin": 311, "xmin": 132}, "name": "pedestrian"}, {"bndbox": {"ymax": 463, "xmax": 150, "ymin": 316, "xmin": 87}, "name": "pedestrian"}, {"bndbox": {"ymax": 643, "xmax": 725, "ymin": 456, "xmin": 663}, "name": "pedestrian"}, {"bndbox": {"ymax": 61, "xmax": 562, "ymin": -2, "xmin": 540}, "name": "pedestrian"}]