[{"bndbox": {"ymax": 107, "xmax": 689, "ymin": 34, "xmin": 664}, "name": "pedestrian"}, {"bndbox": {"ymax": 279, "xmax": 126, "ymin": 172, "xmin": 77}, "name": "pedestrian"}, {"bndbox": {"ymax": 296, "xmax": 149, "ymin": 185, "xmin": 100}, "name": "pedestrian"}, {"bndbox": {"ymax": 142, "xmax": 805, "ymin": 60, "xmin": 774}, "name": "pedestrian"}, {"bndbox": {"ymax": 289, "xmax": 611, "ymin": 176, "xmin": 575}, "name": "pedestrian"}, {"bndbox": {"ymax": 153, "xmax": 482, "ymin": 70, "xmin": 453}, "name": "pedestrian"}, {"bndbox": {"ymax": 160, "xmax": 514, "ymin": 75, "xmin": 485}, "name": "pedestrian"}, {"bndbox": {"ymax": 216, "xmax": 739, "ymin": 119, "xmin": 705}, "name": "pedestrian"}, {"bndbox": {"ymax": 164, "xmax": 312, "ymin": 80, "xmin": 281}, "name": "pedestrian"}, {"bndbox": {"ymax": 152, "xmax": 288, "ymin": 70, "xmin": 256}, "name": "pedestrian"}, {"bndbox": {"ymax": 184, "xmax": 326, "ymin": 95, "xmin": 293}, "name": "pedestrian"}, {"bndbox": {"ymax": 265, "xmax": 172, "ymin": 160, "xmin": 127}, "name": "pedestrian"}, {"bndbox": {"ymax": 264, "xmax": 146, "ymin": 159, "xmin": 100}, "name": "pedestrian"}, {"bndbox": {"ymax": 478, "xmax": 779, "ymin": 327, "xmin": 725}, "name": "pedestrian"}, {"bndbox": {"ymax": 198, "xmax": 196, "ymin": 107, "xmin": 158}, "name": "pedestrian"}, {"bndbox": {"ymax": 190, "xmax": 914, "ymin": 96, "xmin": 872}, "name": "pedestrian"}, {"bndbox": {"ymax": 383, "xmax": 915, "ymin": 250, "xmin": 861}, "name": "pedestrian"}, {"bndbox": {"ymax": 260, "xmax": 76, "ymin": 156, "xmin": 24}, "name": "pedestrian"}]