[{"bndbox": {"ymax": 121, "xmax": 641, "ymin": 45, "xmin": 615}, "name": "pedestrian"}, {"bndbox": {"ymax": 310, "xmax": 83, "ymin": 195, "xmin": 28}, "name": "pedestrian"}, {"bndbox": {"ymax": 324, "xmax": 107, "ymin": 207, "xmin": 53}, "name": "pedestrian"}, {"bndbox": {"ymax": 125, "xmax": 821, "ymin": 46, "xmin": 790}, "name": "pedestrian"}, {"bndbox": {"ymax": 333, "xmax": 575, "ymin": 211, "xmin": 536}, "name": "pedestrian"}, {"bndbox": {"ymax": 135, "xmax": 503, "ymin": 56, "xmin": 475}, "name": "pedestrian"}, {"bndbox": {"ymax": 137, "xmax": 530, "ymin": 57, "xmin": 503}, "name": "pedestrian"}, {"bndbox": {"ymax": 189, "xmax": 766, "ymin": 98, "xmin": 734}, "name": "pedestrian"}, {"bndbox": {"ymax": 150, "xmax": 346, "ymin": 69, "xmin": 316}, "name": "pedestrian"}, {"bndbox": {"ymax": 137, "xmax": 320, "ymin": 58, "xmin": 290}, "name": "pedestrian"}, {"bndbox": {"ymax": 206, "xmax": 279, "ymin": 113, "xmin": 244}, "name": "pedestrian"}, {"bndbox": {"ymax": 293, "xmax": 108, "ymin": 182, "xmin": 56}, "name": "pedestrian"}, {"bndbox": {"ymax": 287, "xmax": 83, "ymin": 177, "xmin": 29}, "name": "pedestrian"}, {"bndbox": {"ymax": 419, "xmax": 816, "ymin": 280, "xmin": 765}, "name": "pedestrian"}, {"bndbox": {"ymax": 172, "xmax": 256, "ymin": 87, "xmin": 222}, "name": "pedestrian"}, {"bndbox": {"ymax": 217, "xmax": 895, "ymin": 118, "xmin": 854}, "name": "pedestrian"}, {"bndbox": {"ymax": 430, "xmax": 910, "ymin": 287, "xmin": 853}, "name": "pedestrian"}, {"bndbox": {"ymax": 230, "xmax": 136, "ymin": 132, "xmin": 92}, "name": "pedestrian"}, {"bndbox": {"ymax": 201, "xmax": 952, "ymin": 104, "xmin": 906}, "name": "pedestrian"}]