[{"bndbox": {"ymax": 140, "xmax": 798, "ymin": 59, "xmin": 767}, "name": "pedestrian"}, {"bndbox": {"ymax": 286, "xmax": 58, "ymin": 176, "xmin": 2}, "name": "pedestrian"}, {"bndbox": {"ymax": 131, "xmax": 412, "ymin": 53, "xmin": 384}, "name": "pedestrian"}, {"bndbox": {"ymax": 163, "xmax": 378, "ymin": 78, "xmin": 348}, "name": "pedestrian"}, {"bndbox": {"ymax": 119, "xmax": 591, "ymin": 43, "xmin": 566}, "name": "pedestrian"}, {"bndbox": {"ymax": 293, "xmax": 802, "ymin": 180, "xmin": 761}, "name": "pedestrian"}, {"bndbox": {"ymax": 232, "xmax": 264, "ymin": 133, "xmin": 226}, "name": "pedestrian"}, {"bndbox": {"ymax": 347, "xmax": 865, "ymin": 222, "xmin": 817}, "name": "pedestrian"}, {"bndbox": {"ymax": 270, "xmax": 886, "ymin": 161, "xmin": 841}, "name": "pedestrian"}, {"bndbox": {"ymax": 327, "xmax": 399, "ymin": 207, "xmin": 357}, "name": "pedestrian"}, {"bndbox": {"ymax": 439, "xmax": 884, "ymin": 295, "xmin": 828}, "name": "pedestrian"}, {"bndbox": {"ymax": 400, "xmax": 270, "ymin": 266, "xmin": 218}, "name": "pedestrian"}, {"bndbox": {"ymax": 403, "xmax": 231, "ymin": 269, "xmin": 177}, "name": "pedestrian"}, {"bndbox": {"ymax": 543, "xmax": 795, "ymin": 378, "xmin": 736}, "name": "pedestrian"}, {"bndbox": {"ymax": 71, "xmax": 536, "ymin": 6, "xmin": 513}, "name": "pedestrian"}]