[{"bndbox": {"ymax": 124, "xmax": 810, "ymin": 46, "xmin": 779}, "name": "pedestrian"}, {"bndbox": {"ymax": 116, "xmax": 442, "ymin": 42, "xmin": 415}, "name": "pedestrian"}, {"bndbox": {"ymax": 150, "xmax": 408, "ymin": 68, "xmin": 378}, "name": "pedestrian"}, {"bndbox": {"ymax": 129, "xmax": 569, "ymin": 51, "xmin": 543}, "name": "pedestrian"}, {"bndbox": {"ymax": 256, "xmax": 831, "ymin": 150, "xmin": 791}, "name": "pedestrian"}, {"bndbox": {"ymax": 207, "xmax": 296, "ymin": 113, "xmin": 261}, "name": "pedestrian"}, {"bndbox": {"ymax": 381, "xmax": 842, "ymin": 249, "xmin": 793}, "name": "pedestrian"}, {"bndbox": {"ymax": 302, "xmax": 864, "ymin": 186, "xmin": 819}, "name": "pedestrian"}, {"bndbox": {"ymax": 299, "xmax": 447, "ymin": 184, "xmin": 407}, "name": "pedestrian"}, {"bndbox": {"ymax": 395, "xmax": 908, "ymin": 259, "xmin": 853}, "name": "pedestrian"}, {"bndbox": {"ymax": 362, "xmax": 322, "ymin": 235, "xmin": 275}, "name": "pedestrian"}, {"bndbox": {"ymax": 362, "xmax": 279, "ymin": 236, "xmin": 230}, "name": "pedestrian"}, {"bndbox": {"ymax": 482, "xmax": 843, "ymin": 329, "xmin": 787}, "name": "pedestrian"}, {"bndbox": {"ymax": 79, "xmax": 514, "ymin": 12, "xmin": 490}, "name": "pedestrian"}, {"bndbox": {"ymax": 404, "xmax": 92, "ymin": 270, "xmin": 30}, "name": "pedestrian"}, {"bndbox": {"ymax": 353, "xmax": 68, "ymin": 229, "xmin": 7}, "name": "pedestrian"}, {"bndbox": {"ymax": 333, "xmax": 49, "ymin": 213, "xmin": -12}, "name": "pedestrian"}]