[{"bndbox": {"ymax": 311, "xmax": 56, "ymin": 196, "xmin": -3}, "name": "pedestrian"}, {"bndbox": {"ymax": 168, "xmax": 262, "ymin": 83, "xmin": 228}, "name": "pedestrian"}, {"bndbox": {"ymax": 170, "xmax": 466, "ymin": 84, "xmin": 435}, "name": "pedestrian"}, {"bndbox": {"ymax": 174, "xmax": 496, "ymin": 87, "xmin": 466}, "name": "pedestrian"}, {"bndbox": {"ymax": 395, "xmax": 388, "ymin": 261, "xmin": 340}, "name": "pedestrian"}, {"bndbox": {"ymax": 546, "xmax": 485, "ymin": 384, "xmin": 430}, "name": "pedestrian"}, {"bndbox": {"ymax": 574, "xmax": 887, "ymin": 398, "xmin": 823}, "name": "pedestrian"}, {"bndbox": {"ymax": 110, "xmax": 854, "ymin": 33, "xmin": 822}, "name": "pedestrian"}, {"bndbox": {"ymax": 58, "xmax": 781, "ymin": -6, "xmin": 755}, "name": "pedestrian"}, {"bndbox": {"ymax": 91, "xmax": 518, "ymin": 21, "xmin": 494}, "name": "pedestrian"}, {"bndbox": {"ymax": 520, "xmax": 896, "ymin": 357, "xmin": 834}, "name": "pedestrian"}, {"bndbox": {"ymax": 60, "xmax": 571, "ymin": -3, "xmin": 549}, "name": "pedestrian"}]