[{"bndbox": {"ymax": 84, "xmax": 830, "ymin": 13, "xmin": 801}, "name": "pedestrian"}, {"bndbox": {"ymax": 75, "xmax": 532, "ymin": 9, "xmin": 509}, "name": "pedestrian"}, {"bndbox": {"ymax": 141, "xmax": 579, "ymin": 61, "xmin": 551}, "name": "pedestrian"}, {"bndbox": {"ymax": 180, "xmax": 489, "ymin": 91, "xmin": 458}, "name": "pedestrian"}, {"bndbox": {"ymax": 172, "xmax": 937, "ymin": 81, "xmin": 894}, "name": "pedestrian"}, {"bndbox": {"ymax": 148, "xmax": 427, "ymin": 66, "xmin": 398}, "name": "pedestrian"}, {"bndbox": {"ymax": 520, "xmax": 777, "ymin": 360, "xmin": 720}, "name": "pedestrian"}, {"bndbox": {"ymax": 416, "xmax": 800, "ymin": 278, "xmin": 749}, "name": "pedestrian"}, {"bndbox": {"ymax": 226, "xmax": 580, "ymin": 127, "xmin": 547}, "name": "pedestrian"}, {"bndbox": {"ymax": 265, "xmax": 471, "ymin": 157, "xmin": 434}, "name": "pedestrian"}, {"bndbox": {"ymax": 263, "xmax": 435, "ymin": 156, "xmin": 398}, "name": "pedestrian"}, {"bndbox": {"ymax": 319, "xmax": 907, "ymin": 200, "xmin": 858}, "name": "pedestrian"}, {"bndbox": {"ymax": 109, "xmax": 422, "ymin": 36, "xmin": 395}, "name": "pedestrian"}, {"bndbox": {"ymax": 269, "xmax": 289, "ymin": 162, "xmin": 248}, "name": "pedestrian"}, {"bndbox": {"ymax": 271, "xmax": 209, "ymin": 165, "xmin": 166}, "name": "pedestrian"}, {"bndbox": {"ymax": 255, "xmax": 180, "ymin": 152, "xmin": 137}, "name": "pedestrian"}, {"bndbox": {"ymax": 256, "xmax": 129, "ymin": 153, "xmin": 82}, "name": "pedestrian"}, {"bndbox": {"ymax": 76, "xmax": 732, "ymin": 8, "xmin": 708}, "name": "pedestrian"}, {"bndbox": {"ymax": 83, "xmax": 506, "ymin": 15, "xmin": 482}, "name": "pedestrian"}, {"bndbox": {"ymax": 246, "xmax": 87, "ymin": 145, "xmin": 37}, "name": "pedestrian"}]