[{"bndbox": {"ymax": 62, "xmax": 845, "ymin": -5, "xmin": 816}, "name": "pedestrian"}, {"bndbox": {"ymax": 152, "xmax": 704, "ymin": 69, "xmin": 676}, "name": "pedestrian"}, {"bndbox": {"ymax": 221, "xmax": 425, "ymin": 123, "xmin": 391}, "name": "pedestrian"}, {"bndbox": {"ymax": 116, "xmax": 502, "ymin": 41, "xmin": 476}, "name": "pedestrian"}, {"bndbox": {"ymax": 672, "xmax": 802, "ymin": 473, "xmin": 736}, "name": "pedestrian"}, {"bndbox": {"ymax": 540, "xmax": 790, "ymin": 375, "xmin": 731}, "name": "pedestrian"}, {"bndbox": {"ymax": 183, "xmax": 646, "ymin": 93, "xmin": 617}, "name": "pedestrian"}, {"bndbox": {"ymax": 209, "xmax": 551, "ymin": 113, "xmin": 519}, "name": "pedestrian"}, {"bndbox": {"ymax": 212, "xmax": 512, "ymin": 115, "xmin": 479}, "name": "pedestrian"}, {"bndbox": {"ymax": 234, "xmax": 912, "ymin": 132, "xmin": 868}, "name": "pedestrian"}, {"bndbox": {"ymax": 134, "xmax": 355, "ymin": 56, "xmin": 326}, "name": "pedestrian"}, {"bndbox": {"ymax": 203, "xmax": 393, "ymin": 110, "xmin": 360}, "name": "pedestrian"}, {"bndbox": {"ymax": 223, "xmax": 274, "ymin": 126, "xmin": 237}, "name": "pedestrian"}, {"bndbox": {"ymax": 207, "xmax": 251, "ymin": 114, "xmin": 215}, "name": "pedestrian"}, {"bndbox": {"ymax": 215, "xmax": 212, "ymin": 121, "xmin": 173}, "name": "pedestrian"}, {"bndbox": {"ymax": 95, "xmax": 776, "ymin": 23, "xmin": 749}, "name": "pedestrian"}, {"bndbox": {"ymax": 109, "xmax": 446, "ymin": 36, "xmin": 420}, "name": "pedestrian"}, {"bndbox": {"ymax": 204, "xmax": 180, "ymin": 111, "xmin": 141}, "name": "pedestrian"}, {"bndbox": {"ymax": 82, "xmax": 873, "ymin": 10, "xmin": 841}, "name": "pedestrian"}, {"bndbox": {"ymax": 70, "xmax": 535, "ymin": 5, "xmin": 512}, "name": "pedestrian"}]