[{"bndbox": {"ymax": 184, "xmax": 917, "ymin": 92, "xmin": 875}, "name": "pedestrian"}, {"bndbox": {"ymax": 300, "xmax": 195, "ymin": 188, "xmin": 149}, "name": "pedestrian"}, {"bndbox": {"ymax": 66, "xmax": 635, "ymin": 2, "xmin": 613}, "name": "pedestrian"}, {"bndbox": {"ymax": 125, "xmax": 748, "ymin": 47, "xmin": 720}, "name": "pedestrian"}, {"bndbox": {"ymax": 128, "xmax": 657, "ymin": 50, "xmin": 631}, "name": "pedestrian"}, {"bndbox": {"ymax": 131, "xmax": 625, "ymin": 53, "xmin": 599}, "name": "pedestrian"}, {"bndbox": {"ymax": 139, "xmax": 875, "ymin": 56, "xmin": 840}, "name": "pedestrian"}, {"bndbox": {"ymax": 199, "xmax": 229, "ymin": 108, "xmin": 192}, "name": "pedestrian"}, {"bndbox": {"ymax": 114, "xmax": 528, "ymin": 39, "xmin": 502}, "name": "pedestrian"}, {"bndbox": {"ymax": 158, "xmax": 401, "ymin": 74, "xmin": 370}, "name": "pedestrian"}, {"bndbox": {"ymax": 147, "xmax": 384, "ymin": 66, "xmin": 355}, "name": "pedestrian"}, {"bndbox": {"ymax": 156, "xmax": 365, "ymin": 73, "xmin": 334}, "name": "pedestrian"}, {"bndbox": {"ymax": 147, "xmax": 850, "ymin": 63, "xmin": 816}, "name": "pedestrian"}, {"bndbox": {"ymax": 171, "xmax": 289, "ymin": 85, "xmin": 257}, "name": "pedestrian"}, {"bndbox": {"ymax": 154, "xmax": 339, "ymin": 72, "xmin": 309}, "name": "pedestrian"}, {"bndbox": {"ymax": 135, "xmax": 774, "ymin": 55, "xmin": 745}, "name": "pedestrian"}, {"bndbox": {"ymax": 124, "xmax": 389, "ymin": 48, "xmin": 361}, "name": "pedestrian"}, {"bndbox": {"ymax": 78, "xmax": 552, "ymin": 12, "xmin": 528}, "name": "pedestrian"}, {"bndbox": {"ymax": 112, "xmax": 535, "ymin": 38, "xmin": 509}, "name": "pedestrian"}, {"bndbox": {"ymax": 610, "xmax": 399, "ymin": 434, "xmin": 336}, "name": "pedestrian"}]