[{"bndbox": {"ymax": 190, "xmax": 952, "ymin": 95, "xmin": 906}, "name": "pedestrian"}, {"bndbox": {"ymax": 323, "xmax": 149, "ymin": 206, "xmin": 99}, "name": "pedestrian"}, {"bndbox": {"ymax": 57, "xmax": 663, "ymin": -6, "xmin": 641}, "name": "pedestrian"}, {"bndbox": {"ymax": 116, "xmax": 769, "ymin": 40, "xmin": 740}, "name": "pedestrian"}, {"bndbox": {"ymax": 118, "xmax": 676, "ymin": 42, "xmin": 650}, "name": "pedestrian"}, {"bndbox": {"ymax": 121, "xmax": 641, "ymin": 45, "xmin": 616}, "name": "pedestrian"}, {"bndbox": {"ymax": 124, "xmax": 854, "ymin": 45, "xmin": 821}, "name": "pedestrian"}, {"bndbox": {"ymax": 217, "xmax": 204, "ymin": 122, "xmin": 165}, "name": "pedestrian"}, {"bndbox": {"ymax": 99, "xmax": 551, "ymin": 28, "xmin": 526}, "name": "pedestrian"}, {"bndbox": {"ymax": 149, "xmax": 425, "ymin": 67, "xmin": 395}, "name": "pedestrian"}, {"bndbox": {"ymax": 137, "xmax": 409, "ymin": 58, "xmin": 381}, "name": "pedestrian"}, {"bndbox": {"ymax": 147, "xmax": 386, "ymin": 66, "xmin": 357}, "name": "pedestrian"}, {"bndbox": {"ymax": 156, "xmax": 864, "ymin": 70, "xmin": 829}, "name": "pedestrian"}, {"bndbox": {"ymax": 186, "xmax": 265, "ymin": 98, "xmin": 230}, "name": "pedestrian"}, {"bndbox": {"ymax": 142, "xmax": 363, "ymin": 62, "xmin": 333}, "name": "pedestrian"}, {"bndbox": {"ymax": 148, "xmax": 762, "ymin": 66, "xmin": 732}, "name": "pedestrian"}, {"bndbox": {"ymax": 140, "xmax": 358, "ymin": 60, "xmin": 328}, "name": "pedestrian"}, {"bndbox": {"ymax": 89, "xmax": 527, "ymin": 20, "xmin": 503}, "name": "pedestrian"}, {"bndbox": {"ymax": 532, "xmax": 471, "ymin": 372, "xmin": 417}, "name": "pedestrian"}, {"bndbox": {"ymax": 125, "xmax": 511, "ymin": 48, "xmin": 484}, "name": "pedestrian"}]