[{"bndbox": {"ymax": 359, "xmax": 62, "ymin": 234, "xmin": 0}, "name": "pedestrian"}, {"bndbox": {"ymax": 104, "xmax": 798, "ymin": 30, "xmin": 769}, "name": "pedestrian"}, {"bndbox": {"ymax": 101, "xmax": 701, "ymin": 29, "xmin": 676}, "name": "pedestrian"}, {"bndbox": {"ymax": 101, "xmax": 663, "ymin": 29, "xmin": 638}, "name": "pedestrian"}, {"bndbox": {"ymax": 104, "xmax": 850, "ymin": 28, "xmin": 818}, "name": "pedestrian"}, {"bndbox": {"ymax": 242, "xmax": 156, "ymin": 142, "xmin": 112}, "name": "pedestrian"}, {"bndbox": {"ymax": 84, "xmax": 575, "ymin": 16, "xmin": 551}, "name": "pedestrian"}, {"bndbox": {"ymax": 134, "xmax": 465, "ymin": 56, "xmin": 437}, "name": "pedestrian"}, {"bndbox": {"ymax": 122, "xmax": 451, "ymin": 46, "xmin": 424}, "name": "pedestrian"}, {"bndbox": {"ymax": 135, "xmax": 423, "ymin": 56, "xmin": 394}, "name": "pedestrian"}, {"bndbox": {"ymax": 175, "xmax": 870, "ymin": 85, "xmin": 833}, "name": "pedestrian"}, {"bndbox": {"ymax": 217, "xmax": 227, "ymin": 122, "xmin": 188}, "name": "pedestrian"}, {"bndbox": {"ymax": 130, "xmax": 403, "ymin": 53, "xmin": 375}, "name": "pedestrian"}, {"bndbox": {"ymax": 180, "xmax": 742, "ymin": 91, "xmin": 711}, "name": "pedestrian"}, {"bndbox": {"ymax": 167, "xmax": 310, "ymin": 82, "xmin": 278}, "name": "pedestrian"}, {"bndbox": {"ymax": 107, "xmax": 483, "ymin": 34, "xmin": 457}, "name": "pedestrian"}, {"bndbox": {"ymax": 446, "xmax": 558, "ymin": 302, "xmin": 513}, "name": "pedestrian"}, {"bndbox": {"ymax": 234, "xmax": 947, "ymin": 130, "xmin": 899}, "name": "pedestrian"}, {"bndbox": {"ymax": 174, "xmax": 956, "ymin": 82, "xmin": 911}, "name": "pedestrian"}]