[{"bndbox": {"ymax": 89, "xmax": 857, "ymin": 16, "xmin": 826}, "name": "pedestrian"}, {"bndbox": {"ymax": 76, "xmax": 726, "ymin": 9, "xmin": 701}, "name": "pedestrian"}, {"bndbox": {"ymax": 78, "xmax": 702, "ymin": 11, "xmin": 678}, "name": "pedestrian"}, {"bndbox": {"ymax": 74, "xmax": 826, "ymin": 5, "xmin": 798}, "name": "pedestrian"}, {"bndbox": {"ymax": 289, "xmax": 63, "ymin": 178, "xmin": 7}, "name": "pedestrian"}, {"bndbox": {"ymax": 56, "xmax": 619, "ymin": -6, "xmin": 597}, "name": "pedestrian"}, {"bndbox": {"ymax": 115, "xmax": 512, "ymin": 40, "xmin": 486}, "name": "pedestrian"}, {"bndbox": {"ymax": 103, "xmax": 496, "ymin": 31, "xmin": 471}, "name": "pedestrian"}, {"bndbox": {"ymax": 115, "xmax": 485, "ymin": 41, "xmin": 458}, "name": "pedestrian"}, {"bndbox": {"ymax": 207, "xmax": 878, "ymin": 110, "xmin": 839}, "name": "pedestrian"}, {"bndbox": {"ymax": 278, "xmax": 156, "ymin": 170, "xmin": 110}, "name": "pedestrian"}, {"bndbox": {"ymax": 118, "xmax": 468, "ymin": 43, "xmin": 441}, "name": "pedestrian"}, {"bndbox": {"ymax": 231, "xmax": 694, "ymin": 131, "xmin": 661}, "name": "pedestrian"}, {"bndbox": {"ymax": 213, "xmax": 230, "ymin": 119, "xmin": 192}, "name": "pedestrian"}, {"bndbox": {"ymax": 133, "xmax": 394, "ymin": 55, "xmin": 365}, "name": "pedestrian"}, {"bndbox": {"ymax": 340, "xmax": 662, "ymin": 216, "xmin": 621}, "name": "pedestrian"}, {"bndbox": {"ymax": 287, "xmax": 922, "ymin": 174, "xmin": 873}, "name": "pedestrian"}, {"bndbox": {"ymax": 221, "xmax": 930, "ymin": 121, "xmin": 885}, "name": "pedestrian"}, {"bndbox": {"ymax": 171, "xmax": 375, "ymin": 85, "xmin": 344}, "name": "pedestrian"}]