[{"bndbox": {"ymax": 64, "xmax": 584, "ymin": 0, "xmin": 561}, "name": "pedestrian"}, {"bndbox": {"ymax": 69, "xmax": 572, "ymin": 4, "xmin": 550}, "name": "pedestrian"}, {"bndbox": {"ymax": 309, "xmax": 904, "ymin": 192, "xmin": 856}, "name": "pedestrian"}, {"bndbox": {"ymax": 69, "xmax": 547, "ymin": 4, "xmin": 524}, "name": "pedestrian"}, {"bndbox": {"ymax": 429, "xmax": 618, "ymin": 288, "xmin": 572}, "name": "pedestrian"}, {"bndbox": {"ymax": 234, "xmax": 171, "ymin": 136, "xmin": 129}, "name": "pedestrian"}, {"bndbox": {"ymax": 189, "xmax": 871, "ymin": 96, "xmin": 833}, "name": "pedestrian"}, {"bndbox": {"ymax": 427, "xmax": 676, "ymin": 286, "xmin": 629}, "name": "pedestrian"}, {"bndbox": {"ymax": 354, "xmax": 723, "ymin": 228, "xmin": 680}, "name": "pedestrian"}, {"bndbox": {"ymax": 282, "xmax": 150, "ymin": 174, "xmin": 103}, "name": "pedestrian"}, {"bndbox": {"ymax": 120, "xmax": 411, "ymin": 45, "xmin": 384}, "name": "pedestrian"}, {"bndbox": {"ymax": 117, "xmax": 395, "ymin": 42, "xmin": 367}, "name": "pedestrian"}]