[{"bndbox": {"ymax": 55, "xmax": 603, "ymin": -7, "xmin": 581}, "name": "pedestrian"}, {"bndbox": {"ymax": 355, "xmax": 906, "ymin": 228, "xmin": 854}, "name": "pedestrian"}, {"bndbox": {"ymax": 549, "xmax": 608, "ymin": 385, "xmin": 556}, "name": "pedestrian"}, {"bndbox": {"ymax": 283, "xmax": 85, "ymin": 174, "xmin": 32}, "name": "pedestrian"}, {"bndbox": {"ymax": 164, "xmax": 904, "ymin": 75, "xmin": 865}, "name": "pedestrian"}, {"bndbox": {"ymax": 451, "xmax": 494, "ymin": 306, "xmin": 446}, "name": "pedestrian"}, {"bndbox": {"ymax": 382, "xmax": 543, "ymin": 250, "xmin": 501}, "name": "pedestrian"}, {"bndbox": {"ymax": 335, "xmax": 60, "ymin": 215, "xmin": 0}, "name": "pedestrian"}, {"bndbox": {"ymax": 152, "xmax": 342, "ymin": 70, "xmin": 311}, "name": "pedestrian"}, {"bndbox": {"ymax": 148, "xmax": 327, "ymin": 67, "xmin": 297}, "name": "pedestrian"}, {"bndbox": {"ymax": 422, "xmax": 102, "ymin": 284, "xmin": 39}, "name": "pedestrian"}, {"bndbox": {"ymax": 462, "xmax": 900, "ymin": 312, "xmin": 842}, "name": "pedestrian"}]